{
  "publicPath": "/",
  "all": [
    "js/vendor.9fff0859.js",
    "img/space.6531a11d.jpeg",
    "css/vendor.eb020083.css",
    "fonts/flUhRq6tzZclQEJ-Vdg-IuiaDsNa.a7d6a198.woff",
    "fonts/flUhRq6tzZclQEJ-Vdg-IuiaDsNcIhQ8tQ.4c7c4ea2.woff2",
    "favicon.ico",
    "icons/icon-512x512.png",
    "icons/icon-384x384.png",
    "js/app.340b9a29.js",
    "js/403.578c1c5a.js",
    "icons/icon-256x256.png",
    "js/754.b1d4a059.js",
    "fonts/KFOlCnqEu92Fr1MmEU9fBBc-.ddd11dab.woff",
    "fonts/KFOkCnqEu92Fr1MmgVxIIzQ.9391e6e2.woff",
    "fonts/KFOlCnqEu92Fr1MmYUtfBBc-.b555d228.woff",
    "fonts/KFOlCnqEu92Fr1MmSU5fBBc-.877b9231.woff",
    "fonts/KFOlCnqEu92Fr1MmWUlfBBc-.0344cc3c.woff",
    "fonts/KFOmCnqEu92Fr1Mu4mxM.9b78ea3b.woff",
    "icons/icon-192x192.png",
    "js/988.7a5cc85b.js",
    "icons/apple-icon-180x180.png",
    "js/346.43216423.js",
    "icons/apple-icon-167x167.png",
    "icons/ms-icon-144x144.png",
    "icons/apple-icon-152x152.png",
    "icons/favicon-128x128.png",
    "icons/icon-128x128.png",
    "icons/apple-icon-120x120.png",
    "js/983.dbb9607f.js",
    "icons/favicon-96x96.png",
    "icons/safari-pinned-tab.svg",
    "js/597.88b98842.js",
    "js/326.810a86e7.js",
    "icons/favicon-32x32.png",
    "icons/favicon-16x16.png",
    "css/403.7632fbd9.css",
    "js/xlsx.6d1dbc8e.js",
    "css/983.6b7637be.css",
    "css/754.6948a40c.css",
    "css/app.31d6cfe0.css"
  ],
  "initial": [
    "css/vendor.eb020083.css",
    "js/vendor.9fff0859.js",
    "css/app.31d6cfe0.css",
    "js/app.340b9a29.js"
  ],
  "async": [
    "js/403.578c1c5a.js",
    "js/754.b1d4a059.js",
    "js/988.7a5cc85b.js",
    "js/346.43216423.js",
    "js/983.dbb9607f.js",
    "js/597.88b98842.js",
    "js/326.810a86e7.js",
    "css/403.7632fbd9.css",
    "js/xlsx.6d1dbc8e.js",
    "css/983.6b7637be.css",
    "css/754.6948a40c.css"
  ],
  "modules": {
    "11988052": [
      2,
      0,
      13,
      15,
      17,
      12,
      16,
      14,
      4,
      3
    ],
    "29562396": [
      2,
      0,
      13,
      15,
      17,
      12,
      16,
      14,
      4,
      3
    ],
    "32654342": [
      2,
      0,
      13,
      15,
      17,
      12,
      16,
      14,
      4,
      3
    ],
    "38045707": [
      2,
      0,
      13,
      15,
      17,
      12,
      16,
      14,
      4,
      3
    ],
    "39865142": [
      2,
      0,
      13,
      15,
      17,
      12,
      16,
      14,
      4,
      3
    ],
    "41283873": [
      2,
      0,
      13,
      15,
      17,
      12,
      16,
      14,
      4,
      3
    ],
    "42171533": [
      2,
      0,
      13,
      15,
      17,
      12,
      16,
      14,
      4,
      3
    ],
    "44584912": [
      2,
      0,
      13,
      15,
      17,
      12,
      16,
      14,
      4,
      3
    ],
    "45660326": [
      31
    ],
    "47907178": [
      2,
      0,
      13,
      15,
      17,
      12,
      16,
      14,
      4,
      3
    ],
    "51309338": [
      2,
      0,
      13,
      15,
      17,
      12,
      16,
      14,
      4,
      3
    ],
    "60744072": [
      2,
      0,
      13,
      15,
      17,
      12,
      16,
      14,
      4,
      3
    ],
    "63535952": [
      2,
      0,
      13,
      15,
      17,
      12,
      16,
      14,
      4,
      3
    ],
    "64054388": [
      2,
      0,
      13,
      15,
      17,
      12,
      16,
      14,
      4,
      3
    ],
    "64484433": [
      2,
      0,
      13,
      15,
      17,
      12,
      16,
      14,
      4,
      3
    ],
    "69072312": [
      2,
      0,
      13,
      15,
      17,
      12,
      16,
      14,
      4,
      3
    ],
    "72733386": [
      2,
      0,
      13,
      15,
      17,
      12,
      16,
      14,
      4,
      3
    ],
    "73943694": [
      2,
      0,
      13,
      15,
      17,
      12,
      16,
      14,
      4,
      3
    ],
    "78627147": [
      2,
      0,
      13,
      15,
      17,
      12,
      16,
      14,
      4,
      3
    ],
    "79488144": [
      2,
      0,
      13,
      15,
      17,
      12,
      16,
      14,
      4,
      3
    ],
    "81275450": [
      2,
      0,
      13,
      15,
      17,
      12,
      16,
      14,
      4,
      3
    ],
    "91808162": [
      2,
      0,
      13,
      15,
      17,
      12,
      16,
      14,
      4,
      3
    ],
    "97213684": [
      2,
      0,
      13,
      15,
      17,
      12,
      16,
      14,
      4,
      3
    ],
    "98338892": [
      2,
      0,
      13,
      15,
      17,
      12,
      16,
      14,
      4,
      3
    ],
    "b6d76972": [
      39,
      8
    ],
    "1d337d18": [
      2,
      0,
      13,
      15,
      17,
      12,
      16,
      14,
      4,
      3
    ],
    "eeb39614": [
      39,
      8
    ],
    "7a476fab": [
      2,
      0,
      13,
      15,
      17,
      12,
      16,
      14,
      4,
      3
    ],
    "031bfe56": [
      39,
      8
    ],
    "728563a1": [
      39,
      8
    ],
    "ccad702e": [
      2,
      0,
      13,
      15,
      17,
      12,
      16,
      14,
      4,
      3
    ],
    "77c1a3ac": [
      2,
      0,
      13,
      15,
      17,
      12,
      16,
      14,
      4,
      3
    ],
    "1ae1fd8a": [
      2,
      0,
      13,
      15,
      17,
      12,
      16,
      14,
      4,
      3
    ],
    "25ddc959": [
      2,
      0,
      13,
      15,
      17,
      12,
      16,
      14,
      4,
      3
    ],
    "c774e638": [
      2,
      0,
      13,
      15,
      17,
      12,
      16,
      14,
      4,
      3
    ],
    "60a4c7f7": [
      2,
      0,
      13,
      15,
      17,
      12,
      16,
      14,
      4,
      3
    ],
    "92462dc4": [
      2,
      0,
      13,
      15,
      17,
      12,
      16,
      14,
      4,
      3
    ],
    "5b045826": [
      2,
      0,
      13,
      15,
      17,
      12,
      16,
      14,
      4,
      3
    ],
    "12bd7580": [
      2,
      0,
      13,
      15,
      17,
      12,
      16,
      14,
      4,
      3
    ],
    "e6d73d72": [
      2,
      0,
      13,
      15,
      17,
      12,
      16,
      14,
      4,
      3
    ],
    "4ec2b2c3": [
      2,
      0,
      13,
      15,
      17,
      12,
      16,
      14,
      4,
      3
    ],
    "f15aaf88": [
      2,
      0,
      13,
      15,
      17,
      12,
      16,
      14,
      4,
      3
    ],
    "13ce050e": [
      2,
      0,
      13,
      15,
      17,
      12,
      16,
      14,
      4,
      3
    ],
    "842128ca": [
      2,
      0,
      13,
      15,
      17,
      12,
      16,
      14,
      4,
      3
    ],
    "58ada9d5": [
      2,
      0,
      13,
      15,
      17,
      12,
      16,
      14,
      4,
      3
    ],
    "c212d8ee": [
      2,
      0,
      13,
      15,
      17,
      12,
      16,
      14,
      4,
      3
    ],
    "1fc0ae3d": [
      2,
      0,
      13,
      15,
      17,
      12,
      16,
      14,
      4,
      3
    ],
    "8a658f2a": [
      2,
      0,
      13,
      15,
      17,
      12,
      16,
      14,
      4,
      3
    ],
    "30ec09ea": [
      2,
      0,
      13,
      15,
      17,
      12,
      16,
      14,
      4,
      3
    ],
    "7572523a": [
      2,
      0,
      13,
      15,
      17,
      12,
      16,
      14,
      4,
      3
    ],
    "139dae00": [
      2,
      0,
      13,
      15,
      17,
      12,
      16,
      14,
      4,
      3
    ],
    "f1bf6c2a": [
      39,
      8
    ],
    "54f520ae": [
      2,
      0,
      13,
      15,
      17,
      12,
      16,
      14,
      4,
      3
    ],
    "27f96a93": [
      2,
      0,
      13,
      15,
      17,
      12,
      16,
      14,
      4,
      3
    ],
    "acd5d3e6": [
      2,
      0,
      13,
      15,
      17,
      12,
      16,
      14,
      4,
      3
    ],
    "4205a22f": [
      2,
      0,
      13,
      15,
      17,
      12,
      16,
      14,
      4,
      3
    ],
    "5d683194": [
      39,
      8
    ],
    "23d8c34c": [
      39,
      8
    ],
    "5c89ccea": [
      2,
      0,
      13,
      15,
      17,
      12,
      16,
      14,
      4,
      3
    ],
    "9f7301a8": [
      2,
      0,
      13,
      15,
      17,
      12,
      16,
      14,
      4,
      3
    ],
    "f3828294": [
      2,
      0,
      13,
      15,
      17,
      12,
      16,
      14,
      4,
      3
    ],
    "3c56158a": [
      2,
      0,
      13,
      15,
      17,
      12,
      16,
      14,
      4,
      3
    ],
    "6191b35b": [
      2,
      0,
      13,
      15,
      17,
      12,
      16,
      14,
      4,
      3
    ],
    "666c634e": [
      2,
      0,
      13,
      15,
      17,
      12,
      16,
      14,
      4,
      3
    ],
    "5da08a72": [
      2,
      0,
      13,
      15,
      17,
      12,
      16,
      14,
      4,
      3
    ],
    "fef56c56": [
      2,
      0,
      13,
      15,
      17,
      12,
      16,
      14,
      4,
      3
    ],
    "38c21e3d": [
      2,
      0,
      13,
      15,
      17,
      12,
      16,
      14,
      4,
      3
    ],
    "2994c7fb": [
      2,
      0,
      13,
      15,
      17,
      12,
      16,
      14,
      4,
      3
    ],
    "59bc1bf1": [
      2,
      0,
      13,
      15,
      17,
      12,
      16,
      14,
      4,
      3
    ],
    "21d80f0b": [
      2,
      0,
      13,
      15,
      17,
      12,
      16,
      14,
      4,
      3
    ],
    "025d2baa": [
      2,
      0,
      13,
      15,
      17,
      12,
      16,
      14,
      4,
      3
    ],
    "2ee05fe5": [
      2,
      0,
      13,
      15,
      17,
      12,
      16,
      14,
      4,
      3
    ],
    "39d16e4e": [
      2,
      0,
      13,
      15,
      17,
      12,
      16,
      14,
      4,
      3
    ],
    "45794a6f": [
      2,
      0,
      13,
      15,
      17,
      12,
      16,
      14,
      4,
      3
    ],
    "4f88e182": [
      2,
      0,
      13,
      15,
      17,
      12,
      16,
      14,
      4,
      3
    ],
    "a92d2714": [
      2,
      0,
      13,
      15,
      17,
      12,
      16,
      14,
      4,
      3
    ],
    "254f03c1": [
      2,
      0,
      13,
      15,
      17,
      12,
      16,
      14,
      4,
      3
    ],
    "5ed75d0e": [
      2,
      0,
      13,
      15,
      17,
      12,
      16,
      14,
      4,
      3
    ],
    "15f0fdca": [
      2,
      0,
      13,
      15,
      17,
      12,
      16,
      14,
      4,
      3
    ],
    "b97ec5e0": [
      2,
      0,
      13,
      15,
      17,
      12,
      16,
      14,
      4,
      3
    ],
    "6f32db0a": [
      2,
      0,
      13,
      15,
      17,
      12,
      16,
      14,
      4,
      3
    ],
    "0986c634": [
      2,
      0,
      13,
      15,
      17,
      12,
      16,
      14,
      4,
      3
    ],
    "94f53a4c": [
      2,
      0,
      13,
      15,
      17,
      12,
      16,
      14,
      4,
      3
    ],
    "7d68687f": [
      2,
      0,
      13,
      15,
      17,
      12,
      16,
      14,
      4,
      3
    ],
    "7ec98e2a": [
      2,
      0,
      13,
      15,
      17,
      12,
      16,
      14,
      4,
      3
    ],
    "29cb3e22": [
      2,
      0,
      13,
      15,
      17,
      12,
      16,
      14,
      4,
      3
    ],
    "90aa08d6": [
      2,
      0,
      13,
      15,
      17,
      12,
      16,
      14,
      4,
      3
    ],
    "1b202a75": [
      2,
      0,
      13,
      15,
      17,
      12,
      16,
      14,
      4,
      3
    ],
    "e832fabe": [
      39,
      8
    ],
    "ca88332c": [
      39,
      8
    ],
    "9aabcdea": [
      2,
      0,
      13,
      15,
      17,
      12,
      16,
      14,
      4,
      3
    ],
    "0e9e9e98": [
      39,
      8
    ],
    "36daff9c": [
      2,
      0,
      13,
      15,
      17,
      12,
      16,
      14,
      4,
      3
    ],
    "a6a68cc4": [
      2,
      0,
      13,
      15,
      17,
      12,
      16,
      14,
      4,
      3
    ],
    "0bb96e1e": [
      2,
      0,
      13,
      15,
      17,
      12,
      16,
      14,
      4,
      3
    ],
    "5c23e3d4": [
      2,
      0,
      13,
      15,
      17,
      12,
      16,
      14,
      4,
      3
    ],
    "d22cbd98": [
      2,
      0,
      13,
      15,
      17,
      12,
      16,
      14,
      4,
      3
    ],
    "b3f3ec1c": [
      2,
      0,
      13,
      15,
      17,
      12,
      16,
      14,
      4,
      3
    ],
    "18297ea0": [
      2,
      0,
      13,
      15,
      17,
      12,
      16,
      14,
      4,
      3
    ],
    "4de7b4e3": [
      2,
      0,
      13,
      15,
      17,
      12,
      16,
      14,
      4,
      3
    ],
    "8d8ff0bc": [
      2,
      0,
      13,
      15,
      17,
      12,
      16,
      14,
      4,
      3
    ],
    "79cf4dfb": [
      2,
      0,
      13,
      15,
      17,
      12,
      16,
      14,
      4,
      3
    ],
    "07a76e98": [
      2,
      0,
      13,
      15,
      17,
      12,
      16,
      14,
      4,
      3
    ],
    "fdc3dcb4": [
      2,
      0,
      13,
      15,
      17,
      12,
      16,
      14,
      4,
      3
    ],
    "f933a272": [
      2,
      0,
      13,
      15,
      17,
      12,
      16,
      14,
      4,
      3
    ],
    "284161e4": [
      2,
      0,
      13,
      15,
      17,
      12,
      16,
      14,
      4,
      3
    ],
    "9407fdb8": [
      2,
      0,
      13,
      15,
      17,
      12,
      16,
      14,
      4,
      3
    ],
    "3e40a7d4": [
      2,
      0,
      13,
      15,
      17,
      12,
      16,
      14,
      4,
      3
    ],
    "4e4e57fe": [
      2,
      0,
      13,
      15,
      17,
      12,
      16,
      14,
      4,
      3
    ],
    "2710c258": [
      2,
      0,
      13,
      15,
      17,
      12,
      16,
      14,
      4,
      3
    ],
    "734b4fbb": [
      2,
      0,
      13,
      15,
      17,
      12,
      16,
      14,
      4,
      3
    ],
    "2dda3d22": [
      2,
      0,
      13,
      15,
      17,
      12,
      16,
      14,
      4,
      3
    ],
    "2577bd28": [
      2,
      0,
      13,
      15,
      17,
      12,
      16,
      14,
      4,
      3
    ],
    "260dcb5f": [
      2,
      0,
      13,
      15,
      17,
      12,
      16,
      14,
      4,
      3
    ],
    "5a0dcfe6": [
      2,
      0,
      13,
      15,
      17,
      12,
      16,
      14,
      4,
      3
    ],
    "e26ecee8": [
      2,
      0,
      13,
      15,
      17,
      12,
      16,
      14,
      4,
      3
    ],
    "2efa04ba": [
      2,
      0,
      13,
      15,
      17,
      12,
      16,
      14,
      4,
      3
    ],
    "6b980735": [
      2,
      0,
      13,
      15,
      17,
      12,
      16,
      14,
      4,
      3
    ],
    "280b6464": [
      2,
      0,
      13,
      15,
      17,
      12,
      16,
      14,
      4,
      3
    ],
    "13ec4d79": [
      2,
      0,
      13,
      15,
      17,
      12,
      16,
      14,
      4,
      3
    ],
    "0b87681a": [
      2,
      0,
      13,
      15,
      17,
      12,
      16,
      14,
      4,
      3
    ],
    "6c057bb0": [
      2,
      0,
      13,
      15,
      17,
      12,
      16,
      14,
      4,
      3
    ],
    "08ee4318": [
      2,
      0,
      13,
      15,
      17,
      12,
      16,
      14,
      4,
      3
    ],
    "2cc1ff4c": [
      2,
      0,
      13,
      15,
      17,
      12,
      16,
      14,
      4,
      3
    ],
    "a62a4fb8": [
      2,
      0,
      13,
      15,
      17,
      12,
      16,
      14,
      4,
      3
    ],
    "048ed4e1": [
      2,
      0,
      13,
      15,
      17,
      12,
      16,
      14,
      4,
      3
    ],
    "67d03988": [
      2,
      0,
      13,
      15,
      17,
      12,
      16,
      14,
      4,
      3
    ],
    "3a8ef444": [
      2,
      0,
      13,
      15,
      17,
      12,
      16,
      14,
      4,
      3
    ],
    "6136f17e": [
      2,
      0,
      13,
      15,
      17,
      12,
      16,
      14,
      4,
      3
    ],
    "cc32b1d2": [
      2,
      0,
      13,
      15,
      17,
      12,
      16,
      14,
      4,
      3
    ],
    "30b5052d": [
      2,
      0,
      13,
      15,
      17,
      12,
      16,
      14,
      4,
      3
    ],
    "83e8713e": [
      2,
      0,
      13,
      15,
      17,
      12,
      16,
      14,
      4,
      3
    ],
    "0b01b6ce": [
      2,
      0,
      13,
      15,
      17,
      12,
      16,
      14,
      4,
      3
    ],
    "6512612a": [
      2,
      0,
      13,
      15,
      17,
      12,
      16,
      14,
      4,
      3
    ],
    "63ec96ae": [
      2,
      0,
      13,
      15,
      17,
      12,
      16,
      14,
      4,
      3
    ],
    "6cf54f9a": [
      2,
      0,
      13,
      15,
      17,
      12,
      16,
      14,
      4,
      3
    ],
    "64601b54": [
      39,
      8
    ],
    "c3e48d72": [
      2,
      0,
      13,
      15,
      17,
      12,
      16,
      14,
      4,
      3
    ],
    "05ed00fa": [
      2,
      0,
      13,
      15,
      17,
      12,
      16,
      14,
      4,
      3
    ],
    "5de75e5f": [
      2,
      0,
      13,
      15,
      17,
      12,
      16,
      14,
      4,
      3
    ],
    "34a22090": [
      2,
      0,
      13,
      15,
      17,
      12,
      16,
      14,
      4,
      3
    ],
    "049b7619": [
      2,
      0,
      13,
      15,
      17,
      12,
      16,
      14,
      4,
      3
    ],
    "3b538c00": [
      2,
      0,
      13,
      15,
      17,
      12,
      16,
      14,
      4,
      3
    ],
    "586a4f70": [
      2,
      0,
      13,
      15,
      17,
      12,
      16,
      14,
      4,
      3
    ],
    "767b79b2": [
      2,
      0,
      13,
      15,
      17,
      12,
      16,
      14,
      4,
      3
    ],
    "6e951d0e": [
      2,
      0,
      13,
      15,
      17,
      12,
      16,
      14,
      4,
      3
    ],
    "1d435061": [
      2,
      0,
      13,
      15,
      17,
      12,
      16,
      14,
      4,
      3
    ],
    "0eca9074": [
      2,
      0,
      13,
      15,
      17,
      12,
      16,
      14,
      4,
      3
    ],
    "869badca": [
      2,
      0,
      13,
      15,
      17,
      12,
      16,
      14,
      4,
      3
    ],
    "abd213c6": [
      2,
      0,
      13,
      15,
      17,
      12,
      16,
      14,
      4,
      3
    ],
    "6e78cce6": [
      38,
      11,
      1
    ],
    "c02ed97a": [
      35,
      9
    ],
    "0c97d589": [
      32
    ],
    "e3a050da": [
      37,
      28
    ],
    "2bc89d13": [
      21
    ],
    "1aeb79fe": [
      19,
      1
    ],
    "77728e10": [
      31
    ],
    "2bd0b1b4": [
      2,
      0,
      13,
      15,
      17,
      12,
      16,
      14,
      4,
      3
    ],
    "33228ffa": [
      2,
      0,
      13,
      15,
      17,
      12,
      16,
      14,
      4,
      3
    ],
    "451fd111": [
      2,
      0,
      13,
      15,
      17,
      12,
      16,
      14,
      4,
      3
    ],
    "6c0cd9c1": [
      2,
      0,
      13,
      15,
      17,
      12,
      16,
      14,
      4,
      3
    ],
    "2dcecf26": [
      2,
      0,
      13,
      15,
      17,
      12,
      16,
      14,
      4,
      3
    ],
    "26b2df3a": [
      2,
      0,
      13,
      15,
      17,
      12,
      16,
      14,
      4,
      3
    ],
    "5e7ccb58": [
      2,
      0,
      13,
      15,
      17,
      12,
      16,
      14,
      4,
      3
    ],
    "65431eb8": [
      2,
      0,
      13,
      15,
      17,
      12,
      16,
      14,
      4,
      3
    ],
    "03e86b14": [
      2,
      0,
      13,
      15,
      17,
      12,
      16,
      14,
      4,
      3
    ],
    "1dc5d386": [
      2,
      0,
      13,
      15,
      17,
      12,
      16,
      14,
      4,
      3
    ],
    "9c8dec08": [
      2,
      0,
      13,
      15,
      17,
      12,
      16,
      14,
      4,
      3
    ],
    "4df7ad17": [
      2,
      0,
      13,
      15,
      17,
      12,
      16,
      14,
      4,
      3
    ],
    "029b8c72": [
      2,
      0,
      13,
      15,
      17,
      12,
      16,
      14,
      4,
      3
    ],
    "1205b50a": [
      2,
      0,
      13,
      15,
      17,
      12,
      16,
      14,
      4,
      3
    ],
    "21df0280": [
      2,
      0,
      13,
      15,
      17,
      12,
      16,
      14,
      4,
      3
    ],
    "57bcfc01": [
      2,
      0,
      13,
      15,
      17,
      12,
      16,
      14,
      4,
      3
    ],
    "7b3c0528": [
      2,
      0,
      13,
      15,
      17,
      12,
      16,
      14,
      4,
      3
    ],
    "074a1320": [
      2,
      0,
      13,
      15,
      17,
      12,
      16,
      14,
      4,
      3
    ],
    "2c24fa9a": [
      2,
      0,
      13,
      15,
      17,
      12,
      16,
      14,
      4,
      3
    ],
    "7933bcbc": [
      2,
      0,
      13,
      15,
      17,
      12,
      16,
      14,
      4,
      3
    ],
    "5d5313c6": [
      2,
      0,
      13,
      15,
      17,
      12,
      16,
      14,
      4,
      3
    ],
    "5ae6c006": [
      2,
      0,
      13,
      15,
      17,
      12,
      16,
      14,
      4,
      3
    ],
    "468a47e6": [
      2,
      0,
      13,
      15,
      17,
      12,
      16,
      14,
      4,
      3
    ],
    "49948dba": [
      2,
      0,
      13,
      15,
      17,
      12,
      16,
      14,
      4,
      3
    ],
    "07256f36": [
      2,
      0,
      13,
      15,
      17,
      12,
      16,
      14,
      4,
      3
    ],
    "5c9adbaa": [
      2,
      0,
      13,
      15,
      17,
      12,
      16,
      14,
      4,
      3
    ],
    "8c429c28": [
      2,
      0,
      13,
      15,
      17,
      12,
      16,
      14,
      4,
      3
    ],
    "8d24560a": [
      2,
      0,
      13,
      15,
      17,
      12,
      16,
      14,
      4,
      3
    ],
    "0fa69cb8": [
      2,
      0,
      13,
      15,
      17,
      12,
      16,
      14,
      4,
      3
    ],
    "27a82d14": [
      2,
      0,
      13,
      15,
      17,
      12,
      16,
      14,
      4,
      3
    ],
    "621ffcac": [
      2,
      0,
      13,
      15,
      17,
      12,
      16,
      14,
      4,
      3
    ],
    "d9a79898": [
      2,
      0,
      13,
      15,
      17,
      12,
      16,
      14,
      4,
      3
    ],
    "32c8460a": [
      2,
      0,
      13,
      15,
      17,
      12,
      16,
      14,
      4,
      3
    ],
    "4e7fc4e8": [
      2,
      0,
      13,
      15,
      17,
      12,
      16,
      14,
      4,
      3
    ],
    "939e9546": [
      39,
      8
    ],
    "461c102e": [
      38,
      11,
      1
    ],
    "9a4f634a": [
      38,
      11,
      1
    ],
    "1f7f0bbc": [
      2,
      0,
      13,
      15,
      17,
      12,
      16,
      14,
      4,
      3
    ],
    "e0b11b94": [
      2,
      0,
      13,
      15,
      17,
      12,
      16,
      14,
      4,
      3
    ],
    "53e68af4": [
      2,
      0,
      13,
      15,
      17,
      12,
      16,
      14,
      4,
      3
    ],
    "83e08118": [
      2,
      0,
      13,
      15,
      17,
      12,
      16,
      14,
      4,
      3
    ],
    "cab05724": [
      2,
      0,
      13,
      15,
      17,
      12,
      16,
      14,
      4,
      3
    ],
    "3f270eda": [
      2,
      0,
      13,
      15,
      17,
      12,
      16,
      14,
      4,
      3
    ],
    "7277da7f": [
      2,
      0,
      13,
      15,
      17,
      12,
      16,
      14,
      4,
      3
    ],
    "347c002c": [
      2,
      0,
      13,
      15,
      17,
      12,
      16,
      14,
      4,
      3
    ],
    "2ba723bf": [
      2,
      0,
      13,
      15,
      17,
      12,
      16,
      14,
      4,
      3
    ],
    "299aaf5b": [
      2,
      0,
      13,
      15,
      17,
      12,
      16,
      14,
      4,
      3
    ],
    "13d3fd63": [
      2,
      0,
      13,
      15,
      17,
      12,
      16,
      14,
      4,
      3
    ],
    "0bcee36d": [
      35,
      9
    ],
    "66c4e850": [
      35,
      9
    ],
    "43d18ee4": [
      2,
      0,
      13,
      15,
      17,
      12,
      16,
      14,
      4,
      3
    ],
    "9ac44a1c": [
      2,
      0,
      13,
      15,
      17,
      12,
      16,
      14,
      4,
      3
    ],
    "3f2fdc04": [
      32
    ],
    "092ec48d": [
      32
    ],
    "46a0ec69": [
      37,
      28
    ],
    "c7af21f0": [
      37,
      28
    ],
    "73a7c0d0": [
      2,
      0,
      13,
      15,
      17,
      12,
      16,
      14,
      4,
      3
    ],
    "24178f8d": [
      2,
      0,
      13,
      15,
      17,
      12,
      16,
      14,
      4,
      3
    ],
    "6632ce93": [
      2,
      0,
      13,
      15,
      17,
      12,
      16,
      14,
      4,
      3
    ],
    "230a8733": [
      21
    ],
    "3d7d5b88": [
      21
    ],
    "2f321034": [
      19,
      1
    ],
    "ef003914": [
      19,
      1
    ],
    "464bebf0": [
      2,
      0,
      13,
      15,
      17,
      12,
      16,
      14,
      4,
      3
    ],
    "f6d5552c": [
      31
    ],
    "5aa753c7": [
      2,
      0,
      13,
      15,
      17,
      12,
      16,
      14,
      4,
      3
    ],
    "2ebc69c2": [
      2,
      0,
      13,
      15,
      17,
      12,
      16,
      14,
      4,
      3
    ],
    "388b9842": [
      2,
      0,
      13,
      15,
      17,
      12,
      16,
      14,
      4,
      3
    ],
    "5310f67e": [
      2,
      0,
      13,
      15,
      17,
      12,
      16,
      14,
      4,
      3
    ],
    "d0624638": [
      2,
      0,
      13,
      15,
      17,
      12,
      16,
      14,
      4,
      3
    ],
    "cc8868c2": [
      2,
      0,
      13,
      15,
      17,
      12,
      16,
      14,
      4,
      3
    ],
    "b0faeb18": [
      2,
      0,
      13,
      15,
      17,
      12,
      16,
      14,
      4,
      3
    ],
    "21095dbd": [
      2,
      0,
      13,
      15,
      17,
      12,
      16,
      14,
      4,
      3
    ],
    "a7e83c0c": [
      2,
      0,
      13,
      15,
      17,
      12,
      16,
      14,
      4,
      3
    ],
    "40640fee": [
      2,
      0,
      13,
      15,
      17,
      12,
      16,
      14,
      4,
      3
    ],
    "659753c2": [
      2,
      0,
      13,
      15,
      17,
      12,
      16,
      14,
      4,
      3
    ],
    "5c107e26": [
      2,
      0,
      13,
      15,
      17,
      12,
      16,
      14,
      4,
      3
    ],
    "c4dc3a7a": [
      2,
      0,
      13,
      15,
      17,
      12,
      16,
      14,
      4,
      3
    ],
    "e16c3310": [
      2,
      0,
      13,
      15,
      17,
      12,
      16,
      14,
      4,
      3
    ],
    "87e6e8dc": [
      2,
      0,
      13,
      15,
      17,
      12,
      16,
      14,
      4,
      3
    ],
    "1b5bf7f9": [
      2,
      0,
      13,
      15,
      17,
      12,
      16,
      14,
      4,
      3
    ],
    "513a2842": [
      2,
      0,
      13,
      15,
      17,
      12,
      16,
      14,
      4,
      3
    ],
    "2f0a332f": [
      2,
      0,
      13,
      15,
      17,
      12,
      16,
      14,
      4,
      3
    ],
    "765d5232": [
      2,
      0,
      13,
      15,
      17,
      12,
      16,
      14,
      4,
      3
    ],
    "2818badb": [
      38,
      11,
      1
    ],
    "0df9d948": [
      38,
      11,
      1
    ],
    "64e2dc6f": [
      2,
      0,
      13,
      15,
      17,
      12,
      16,
      14,
      4,
      3
    ],
    "3b4565e4": [
      2,
      0,
      13,
      15,
      17,
      12,
      16,
      14,
      4,
      3
    ],
    "11b23dc1": [
      2,
      0,
      13,
      15,
      17,
      12,
      16,
      14,
      4,
      3
    ],
    "19b106e1": [
      2,
      0,
      13,
      15,
      17,
      12,
      16,
      14,
      4,
      3
    ],
    "0aae5d3b": [
      2,
      0,
      13,
      15,
      17,
      12,
      16,
      14,
      4,
      3
    ],
    "226604e2": [
      2,
      0,
      13,
      15,
      17,
      12,
      16,
      14,
      4,
      3
    ],
    "1d6b67c0": [
      35,
      9
    ],
    "bbed057a": [
      35,
      9
    ],
    "3617bc1a": [
      2,
      0,
      13,
      15,
      17,
      12,
      16,
      14,
      4,
      3
    ],
    "245aaba7": [
      2,
      0,
      13,
      15,
      17,
      12,
      16,
      14,
      4,
      3
    ],
    "da344c2a": [
      32
    ],
    "5adde2d6": [
      37,
      28
    ],
    "a3cc5d96": [
      37,
      28
    ],
    "307534a2": [
      2,
      0,
      13,
      15,
      17,
      12,
      16,
      14,
      4,
      3
    ],
    "dab5dae6": [
      2,
      0,
      13,
      15,
      17,
      12,
      16,
      14,
      4,
      3
    ],
    "4402bf89": [
      2,
      0,
      13,
      15,
      17,
      12,
      16,
      14,
      4,
      3
    ],
    "7b41a240": [
      21
    ],
    "2009b916": [
      21
    ],
    "112ebae1": [
      19,
      1
    ],
    "38bd233a": [
      19,
      1
    ],
    "d67742d2": [
      31
    ],
    "0a9b07da": [
      31
    ],
    "c830c0f0": [
      2,
      0,
      13,
      15,
      17,
      12,
      16,
      14,
      4,
      3
    ],
    "6f1af58e": [
      2,
      0,
      13,
      15,
      17,
      12,
      16,
      14,
      4,
      3
    ],
    "23650daa": [
      2,
      0,
      13,
      15,
      17,
      12,
      16,
      14,
      4,
      3
    ],
    "572bf5cb": [
      2,
      0,
      13,
      15,
      17,
      12,
      16,
      14,
      4,
      3
    ],
    "7cf343af": [
      2,
      0,
      13,
      15,
      17,
      12,
      16,
      14,
      4,
      3
    ],
    "90ea7eba": [
      2,
      0,
      13,
      15,
      17,
      12,
      16,
      14,
      4,
      3
    ],
    "19ff6ac7": [
      2,
      0,
      13,
      15,
      17,
      12,
      16,
      14,
      4,
      3
    ],
    "099d8030": [
      2,
      0,
      13,
      15,
      17,
      12,
      16,
      14,
      4,
      3
    ],
    "5488a879": [
      2,
      0,
      13,
      15,
      17,
      12,
      16,
      14,
      4,
      3
    ],
    "e7978b6a": [
      2,
      0,
      13,
      15,
      17,
      12,
      16,
      14,
      4,
      3
    ],
    "6b600f2a": [
      2,
      0,
      13,
      15,
      17,
      12,
      16,
      14,
      4,
      3
    ],
    "08926322": [
      2,
      0,
      13,
      15,
      17,
      12,
      16,
      14,
      4,
      3
    ],
    "0e132dfe": [
      2,
      0,
      13,
      15,
      17,
      12,
      16,
      14,
      4,
      3
    ],
    "80a83054": [
      2,
      0,
      13,
      15,
      17,
      12,
      16,
      14,
      4,
      3
    ],
    "cb63c0a4": [
      2,
      0,
      13,
      15,
      17,
      12,
      16,
      14,
      4,
      3
    ],
    "af223e50": [
      2,
      0,
      13,
      15,
      17,
      12,
      16,
      14,
      4,
      3
    ],
    "5487a596": [
      2,
      0,
      13,
      15,
      17,
      12,
      16,
      14,
      4,
      3
    ],
    "7fa82d12": [
      2,
      0,
      13,
      15,
      17,
      12,
      16,
      14,
      4,
      3
    ],
    "566168a4": [
      2,
      0,
      13,
      15,
      17,
      12,
      16,
      14,
      4,
      3
    ],
    "19ec15cd": [
      2,
      0,
      13,
      15,
      17,
      12,
      16,
      14,
      4,
      3
    ],
    "0d23ad01": [
      38,
      11,
      1
    ],
    "c1b8cdd6": [
      2,
      0,
      13,
      15,
      17,
      12,
      16,
      14,
      4,
      3
    ],
    "57e74336": [
      2,
      0,
      13,
      15,
      17,
      12,
      16,
      14,
      4,
      3
    ],
    "32a45a6e": [
      2,
      0,
      13,
      15,
      17,
      12,
      16,
      14,
      4,
      3
    ],
    "4609ac2f": [
      2,
      0,
      13,
      15,
      17,
      12,
      16,
      14,
      4,
      3
    ],
    "9af91482": [
      2,
      0,
      13,
      15,
      17,
      12,
      16,
      14,
      4,
      3
    ],
    "302d9ed4": [
      35,
      9
    ],
    "0e4d2361": [
      2,
      0,
      13,
      15,
      17,
      12,
      16,
      14,
      4,
      3
    ],
    "77e53f41": [
      2,
      0,
      13,
      15,
      17,
      12,
      16,
      14,
      4,
      3
    ],
    "31fccbd0": [
      2,
      0,
      13,
      15,
      17,
      12,
      16,
      14,
      4,
      3
    ],
    "013a5e06": [
      37,
      28
    ],
    "4108e9b6": [
      2,
      0,
      13,
      15,
      17,
      12,
      16,
      14,
      4,
      3
    ],
    "755ee84a": [
      2,
      0,
      13,
      15,
      17,
      12,
      16,
      14,
      4,
      3
    ],
    "2358f7e0": [
      2,
      0,
      13,
      15,
      17,
      12,
      16,
      14,
      4,
      3
    ],
    "52501d1e": [
      2,
      0,
      13,
      15,
      17,
      12,
      16,
      14,
      4,
      3
    ],
    "6df0ea10": [
      2,
      0,
      13,
      15,
      17,
      12,
      16,
      14,
      4,
      3
    ],
    "6963617b": [
      2,
      0,
      13,
      15,
      17,
      12,
      16,
      14,
      4,
      3
    ],
    "68305b36": [
      2,
      0,
      13,
      15,
      17,
      12,
      16,
      14,
      4,
      3
    ],
    "29d89dfc": [
      2,
      0,
      13,
      15,
      17,
      12,
      16,
      14,
      4,
      3
    ],
    "3f305bfe": [
      2,
      0,
      13,
      15,
      17,
      12,
      16,
      14,
      4,
      3
    ],
    "3a41cc4e": [
      2,
      0,
      13,
      15,
      17,
      12,
      16,
      14,
      4,
      3
    ],
    "982b8746": [
      2,
      0,
      13,
      15,
      17,
      12,
      16,
      14,
      4,
      3
    ],
    "05bd046e": [
      2,
      0,
      13,
      15,
      17,
      12,
      16,
      14,
      4,
      3
    ],
    "300d8181": [
      2,
      0,
      13,
      15,
      17,
      12,
      16,
      14,
      4,
      3
    ],
    "6093c3c7": [
      2,
      0,
      13,
      15,
      17,
      12,
      16,
      14,
      4,
      3
    ],
    "07fd935b": [
      2,
      0,
      13,
      15,
      17,
      12,
      16,
      14,
      4,
      3
    ],
    "20a52738": [
      2,
      0,
      13,
      15,
      17,
      12,
      16,
      14,
      4,
      3
    ],
    "46875cf8": [
      2,
      0,
      13,
      15,
      17,
      12,
      16,
      14,
      4,
      3
    ],
    "1ea7f8b4": [
      2,
      0,
      13,
      15,
      17,
      12,
      16,
      14,
      4,
      3
    ],
    "302fe8be": [
      2,
      0,
      13,
      15,
      17,
      12,
      16,
      14,
      4,
      3
    ],
    "3cf68a07": [
      2,
      0,
      13,
      15,
      17,
      12,
      16,
      14,
      4,
      3
    ],
    "1ec418dd": [
      2,
      0,
      13,
      15,
      17,
      12,
      16,
      14,
      4,
      3
    ],
    "5deaeecf": [
      2,
      0,
      13,
      15,
      17,
      12,
      16,
      14,
      4,
      3
    ],
    "64e9977f": [
      2,
      0,
      13,
      15,
      17,
      12,
      16,
      14,
      4,
      3
    ],
    "73504cfb": [
      2,
      0,
      13,
      15,
      17,
      12,
      16,
      14,
      4,
      3
    ],
    "202cca47": [
      2,
      0,
      13,
      15,
      17,
      12,
      16,
      14,
      4,
      3
    ],
    "4a6148f4": [
      2,
      0,
      13,
      15,
      17,
      12,
      16,
      14,
      4,
      3
    ],
    "75d58e14": [
      2,
      0,
      13,
      15,
      17,
      12,
      16,
      14,
      4,
      3
    ],
    "47a75aca": [
      2,
      0,
      13,
      15,
      17,
      12,
      16,
      14,
      4,
      3
    ],
    "0941f19a": [
      2,
      0,
      13,
      15,
      17,
      12,
      16,
      14,
      4,
      3
    ],
    "0d0611f8": [
      2,
      0,
      13,
      15,
      17,
      12,
      16,
      14,
      4,
      3
    ],
    "3cbb93a2": [
      2,
      0,
      13,
      15,
      17,
      12,
      16,
      14,
      4,
      3
    ],
    "a6c31640": [
      2,
      0,
      13,
      15,
      17,
      12,
      16,
      14,
      4,
      3
    ],
    "2f23701d": [
      2,
      0,
      13,
      15,
      17,
      12,
      16,
      14,
      4,
      3
    ],
    "5366107e": [
      2,
      0,
      13,
      15,
      17,
      12,
      16,
      14,
      4,
      3
    ],
    "2e632e41": [
      2,
      0,
      13,
      15,
      17,
      12,
      16,
      14,
      4,
      3
    ],
    "30fdb887": [
      2,
      0,
      13,
      15,
      17,
      12,
      16,
      14,
      4,
      3
    ],
    "78d14154": [
      2,
      0,
      13,
      15,
      17,
      12,
      16,
      14,
      4,
      3
    ],
    "0d17fb8a": [
      2,
      0,
      13,
      15,
      17,
      12,
      16,
      14,
      4,
      3
    ],
    "98f17ba0": [
      2,
      0,
      13,
      15,
      17,
      12,
      16,
      14,
      4,
      3
    ],
    "2da3db73": [
      2,
      0,
      13,
      15,
      17,
      12,
      16,
      14,
      4,
      3
    ],
    "4b1f815e": [
      2,
      0,
      13,
      15,
      17,
      12,
      16,
      14,
      4,
      3
    ],
    "9262d59c": [
      2,
      0,
      13,
      15,
      17,
      12,
      16,
      14,
      4,
      3
    ],
    "c678ec36": [
      2,
      0,
      13,
      15,
      17,
      12,
      16,
      14,
      4,
      3
    ],
    "47c178fd": [
      2,
      0,
      13,
      15,
      17,
      12,
      16,
      14,
      4,
      3
    ],
    "9ee7bb44": [
      2,
      0,
      13,
      15,
      17,
      12,
      16,
      14,
      4,
      3
    ],
    "ce652622": [
      2,
      0,
      13,
      15,
      17,
      12,
      16,
      14,
      4,
      3
    ],
    "952de184": [
      2,
      0,
      13,
      15,
      17,
      12,
      16,
      14,
      4,
      3
    ],
    "338e0ce0": [
      2,
      0,
      13,
      15,
      17,
      12,
      16,
      14,
      4,
      3
    ],
    "2da688ae": [
      2,
      0,
      13,
      15,
      17,
      12,
      16,
      14,
      4,
      3
    ],
    "0dcb40bc": [
      2,
      0,
      13,
      15,
      17,
      12,
      16,
      14,
      4,
      3
    ],
    "7fbcc5f7": [
      2,
      0,
      13,
      15,
      17,
      12,
      16,
      14,
      4,
      3
    ],
    "3529fc78": [
      2,
      0,
      13,
      15,
      17,
      12,
      16,
      14,
      4,
      3
    ],
    "4c41cd39": [
      2,
      0,
      13,
      15,
      17,
      12,
      16,
      14,
      4,
      3
    ],
    "3598fbf5": [
      2,
      0,
      13,
      15,
      17,
      12,
      16,
      14,
      4,
      3
    ],
    "38b3a4fe": [
      2,
      0,
      13,
      15,
      17,
      12,
      16,
      14,
      4,
      3
    ],
    "27ccdf66": [
      2,
      0,
      13,
      15,
      17,
      12,
      16,
      14,
      4,
      3
    ],
    "6f93b64c": [
      2,
      0,
      13,
      15,
      17,
      12,
      16,
      14,
      4,
      3
    ],
    "79605ad0": [
      2,
      0,
      13,
      15,
      17,
      12,
      16,
      14,
      4,
      3
    ],
    "37db3730": [
      2,
      0,
      13,
      15,
      17,
      12,
      16,
      14,
      4,
      3
    ],
    "250f1d6d": [
      2,
      0,
      13,
      15,
      17,
      12,
      16,
      14,
      4,
      3
    ],
    "2c3f6d2e": [
      2,
      0,
      13,
      15,
      17,
      12,
      16,
      14,
      4,
      3
    ],
    "5801e415": [
      2,
      0,
      13,
      15,
      17,
      12,
      16,
      14,
      4,
      3
    ],
    "00f733c5": [
      2,
      0,
      13,
      15,
      17,
      12,
      16,
      14,
      4,
      3
    ],
    "61af2ac7": [
      2,
      0,
      13,
      15,
      17,
      12,
      16,
      14,
      4,
      3
    ],
    "5a5dbda1": [
      2,
      0,
      13,
      15,
      17,
      12,
      16,
      14,
      4,
      3
    ],
    "76167cf7": [
      2,
      0,
      13,
      15,
      17,
      12,
      16,
      14,
      4,
      3
    ],
    "cf3a5a58": [
      2,
      0,
      13,
      15,
      17,
      12,
      16,
      14,
      4,
      3
    ],
    "587ac155": [
      2,
      0,
      13,
      15,
      17,
      12,
      16,
      14,
      4,
      3
    ],
    "06a2261b": [
      2,
      0,
      13,
      15,
      17,
      12,
      16,
      14,
      4,
      3
    ],
    "2ff5100c": [
      2,
      0,
      13,
      15,
      17,
      12,
      16,
      14,
      4,
      3
    ],
    "27ecc0f1": [
      2,
      0,
      13,
      15,
      17,
      12,
      16,
      14,
      4,
      3
    ],
    "0aae09b6": [
      2,
      0,
      13,
      15,
      17,
      12,
      16,
      14,
      4,
      3
    ],
    "c0c780d6": [
      2,
      0,
      13,
      15,
      17,
      12,
      16,
      14,
      4,
      3
    ],
    "c4279ed4": [
      2,
      0,
      13,
      15,
      17,
      12,
      16,
      14,
      4,
      3
    ],
    "12f1fffc": [
      2,
      0,
      13,
      15,
      17,
      12,
      16,
      14,
      4,
      3
    ],
    "6743abd3": [
      2,
      0,
      13,
      15,
      17,
      12,
      16,
      14,
      4,
      3
    ],
    "3b482018": [
      2,
      0,
      13,
      15,
      17,
      12,
      16,
      14,
      4,
      3
    ],
    "52d470d7": [
      2,
      0,
      13,
      15,
      17,
      12,
      16,
      14,
      4,
      3
    ],
    "4b0bdac3": [
      2,
      0,
      13,
      15,
      17,
      12,
      16,
      14,
      4,
      3
    ],
    "7bf48c75": [
      2,
      0,
      13,
      15,
      17,
      12,
      16,
      14,
      4,
      3
    ],
    "de088776": [
      2,
      0,
      13,
      15,
      17,
      12,
      16,
      14,
      4,
      3
    ],
    "1e63ddb8": [
      2,
      0,
      13,
      15,
      17,
      12,
      16,
      14,
      4,
      3
    ],
    "52731a80": [
      2,
      0,
      13,
      15,
      17,
      12,
      16,
      14,
      4,
      3
    ],
    "c771b1e8": [
      2,
      0,
      13,
      15,
      17,
      12,
      16,
      14,
      4,
      3
    ],
    "166a5b34": [
      2,
      0,
      13,
      15,
      17,
      12,
      16,
      14,
      4,
      3
    ],
    "c9778854": [
      2,
      0,
      13,
      15,
      17,
      12,
      16,
      14,
      4,
      3
    ],
    "c2c43fcc": [
      2,
      0,
      13,
      15,
      17,
      12,
      16,
      14,
      4,
      3
    ],
    "0231412f": [
      2,
      0,
      13,
      15,
      17,
      12,
      16,
      14,
      4,
      3
    ],
    "67b4a350": [
      2,
      0,
      13,
      15,
      17,
      12,
      16,
      14,
      4,
      3
    ],
    "266cbf50": [
      2,
      0,
      13,
      15,
      17,
      12,
      16,
      14,
      4,
      3
    ],
    "bb707af0": [
      2,
      0,
      13,
      15,
      17,
      12,
      16,
      14,
      4,
      3
    ],
    "0a42680c": [
      2,
      0,
      13,
      15,
      17,
      12,
      16,
      14,
      4,
      3
    ],
    "47abfa34": [
      2,
      0,
      13,
      15,
      17,
      12,
      16,
      14,
      4,
      3
    ],
    "67f82789": [
      2,
      0,
      13,
      15,
      17,
      12,
      16,
      14,
      4,
      3
    ],
    "20106f16": [
      2,
      0,
      13,
      15,
      17,
      12,
      16,
      14,
      4,
      3
    ],
    "469989ec": [
      2,
      0,
      13,
      15,
      17,
      12,
      16,
      14,
      4,
      3
    ],
    "3c3a56d0": [
      2,
      0,
      13,
      15,
      17,
      12,
      16,
      14,
      4,
      3
    ],
    "4cdb2ebe": [
      2,
      0,
      13,
      15,
      17,
      12,
      16,
      14,
      4,
      3
    ],
    "f4728f6c": [
      2,
      0,
      13,
      15,
      17,
      12,
      16,
      14,
      4,
      3
    ],
    "65c745a4": [
      2,
      0,
      13,
      15,
      17,
      12,
      16,
      14,
      4,
      3
    ],
    "56f2fc0a": [
      2,
      0,
      13,
      15,
      17,
      12,
      16,
      14,
      4,
      3
    ],
    "7e4c252b": [
      2,
      0,
      13,
      15,
      17,
      12,
      16,
      14,
      4,
      3
    ],
    "96eabce6": [
      2,
      0,
      13,
      15,
      17,
      12,
      16,
      14,
      4,
      3
    ],
    "3bc1ec0e": [
      2,
      0,
      13,
      15,
      17,
      12,
      16,
      14,
      4,
      3
    ],
    "4f4c13f2": [
      2,
      0,
      13,
      15,
      17,
      12,
      16,
      14,
      4,
      3
    ],
    "20f011c4": [
      2,
      0,
      13,
      15,
      17,
      12,
      16,
      14,
      4,
      3
    ],
    "2a1b317a": [
      2,
      0,
      13,
      15,
      17,
      12,
      16,
      14,
      4,
      3
    ],
    "6ed13744": [
      2,
      0,
      13,
      15,
      17,
      12,
      16,
      14,
      4,
      3
    ],
    "c7ed6b6e": [
      2,
      0,
      13,
      15,
      17,
      12,
      16,
      14,
      4,
      3
    ],
    "c4f4843a": [
      2,
      0,
      13,
      15,
      17,
      12,
      16,
      14,
      4,
      3
    ],
    "7432bebe": [
      2,
      0,
      13,
      15,
      17,
      12,
      16,
      14,
      4,
      3
    ],
    "51068fa4": [
      2,
      0,
      13,
      15,
      17,
      12,
      16,
      14,
      4,
      3
    ],
    "7a81bddd": [
      2,
      0,
      13,
      15,
      17,
      12,
      16,
      14,
      4,
      3
    ],
    "091bd15c": [
      2,
      0,
      13,
      15,
      17,
      12,
      16,
      14,
      4,
      3
    ],
    "bada29fc": [
      2,
      0,
      13,
      15,
      17,
      12,
      16,
      14,
      4,
      3
    ],
    "48d1d42e": [
      2,
      0,
      13,
      15,
      17,
      12,
      16,
      14,
      4,
      3
    ],
    "4206c351": [
      2,
      0,
      13,
      15,
      17,
      12,
      16,
      14,
      4,
      3
    ],
    "163f2e76": [
      2,
      0,
      13,
      15,
      17,
      12,
      16,
      14,
      4,
      3
    ],
    "61d84826": [
      2,
      0,
      13,
      15,
      17,
      12,
      16,
      14,
      4,
      3
    ],
    "5f864517": [
      2,
      0,
      13,
      15,
      17,
      12,
      16,
      14,
      4,
      3
    ],
    "d01007f8": [
      2,
      0,
      13,
      15,
      17,
      12,
      16,
      14,
      4,
      3
    ],
    "700ccbc3": [
      2,
      0,
      13,
      15,
      17,
      12,
      16,
      14,
      4,
      3
    ],
    "d3eeb604": [
      2,
      0,
      13,
      15,
      17,
      12,
      16,
      14,
      4,
      3
    ],
    "6b4f690a": [
      2,
      0,
      13,
      15,
      17,
      12,
      16,
      14,
      4,
      3
    ],
    "727e39b0": [
      2,
      0,
      13,
      15,
      17,
      12,
      16,
      14,
      4,
      3
    ],
    "ab2e543c": [
      2,
      0,
      13,
      15,
      17,
      12,
      16,
      14,
      4,
      3
    ],
    "5b2b7d36": [
      2,
      0,
      13,
      15,
      17,
      12,
      16,
      14,
      4,
      3
    ],
    "d50c3878": [
      2,
      0,
      13,
      15,
      17,
      12,
      16,
      14,
      4,
      3
    ],
    "32abff68": [
      2,
      0,
      13,
      15,
      17,
      12,
      16,
      14,
      4,
      3
    ],
    "37f46204": [
      2,
      0,
      13,
      15,
      17,
      12,
      16,
      14,
      4,
      3
    ],
    "2896fd58": [
      2,
      0,
      13,
      15,
      17,
      12,
      16,
      14,
      4,
      3
    ],
    "6aab1068": [
      2,
      0,
      13,
      15,
      17,
      12,
      16,
      14,
      4,
      3
    ],
    "6fa7ac0d": [
      2,
      0,
      13,
      15,
      17,
      12,
      16,
      14,
      4,
      3
    ],
    "89d85b94": [
      2,
      0,
      13,
      15,
      17,
      12,
      16,
      14,
      4,
      3
    ],
    "144f01e9": [
      2,
      0,
      13,
      15,
      17,
      12,
      16,
      14,
      4,
      3
    ],
    "eb06dca2": [
      2,
      0,
      13,
      15,
      17,
      12,
      16,
      14,
      4,
      3
    ],
    "a27ce348": [
      2,
      0,
      13,
      15,
      17,
      12,
      16,
      14,
      4,
      3
    ],
    "635b148a": [
      2,
      0,
      13,
      15,
      17,
      12,
      16,
      14,
      4,
      3
    ],
    "590bb94e": [
      2,
      0,
      13,
      15,
      17,
      12,
      16,
      14,
      4,
      3
    ],
    "30d847f2": [
      2,
      0,
      13,
      15,
      17,
      12,
      16,
      14,
      4,
      3
    ],
    "11c64114": [
      2,
      0,
      13,
      15,
      17,
      12,
      16,
      14,
      4,
      3
    ],
    "8ba28636": [
      2,
      0,
      13,
      15,
      17,
      12,
      16,
      14,
      4,
      3
    ],
    "a4c3a910": [
      2,
      0,
      13,
      15,
      17,
      12,
      16,
      14,
      4,
      3
    ],
    "24ccf6e4": [
      2,
      0,
      13,
      15,
      17,
      12,
      16,
      14,
      4,
      3
    ],
    "7a7f4706": [
      2,
      0,
      13,
      15,
      17,
      12,
      16,
      14,
      4,
      3
    ],
    "7653d752": [
      2,
      0,
      13,
      15,
      17,
      12,
      16,
      14,
      4,
      3
    ],
    "f6bb214c": [
      2,
      0,
      13,
      15,
      17,
      12,
      16,
      14,
      4,
      3
    ],
    "64808a41": [
      2,
      0,
      13,
      15,
      17,
      12,
      16,
      14,
      4,
      3
    ],
    "099e7eae": [
      2,
      0,
      13,
      15,
      17,
      12,
      16,
      14,
      4,
      3
    ],
    "4fd2e552": [
      2,
      0,
      13,
      15,
      17,
      12,
      16,
      14,
      4,
      3
    ],
    "239ca704": [
      2,
      0,
      13,
      15,
      17,
      12,
      16,
      14,
      4,
      3
    ],
    "1c246ea6": [
      2,
      0,
      13,
      15,
      17,
      12,
      16,
      14,
      4,
      3
    ],
    "d0bbef08": [
      2,
      0,
      13,
      15,
      17,
      12,
      16,
      14,
      4,
      3
    ],
    "df8acece": [
      2,
      0,
      13,
      15,
      17,
      12,
      16,
      14,
      4,
      3
    ],
    "cef14b38": [
      2,
      0,
      13,
      15,
      17,
      12,
      16,
      14,
      4,
      3
    ],
    "7ed6a417": [
      2,
      0,
      13,
      15,
      17,
      12,
      16,
      14,
      4,
      3
    ],
    "329fa342": [
      2,
      0,
      13,
      15,
      17,
      12,
      16,
      14,
      4,
      3
    ],
    "72e63d96": [
      2,
      0,
      13,
      15,
      17,
      12,
      16,
      14,
      4,
      3
    ],
    "5382fafc": [
      2,
      0,
      13,
      15,
      17,
      12,
      16,
      14,
      4,
      3
    ],
    "4fd3ce10": [
      2,
      0,
      13,
      15,
      17,
      12,
      16,
      14,
      4,
      3
    ],
    "5d26b063": [
      2,
      0,
      13,
      15,
      17,
      12,
      16,
      14,
      4,
      3
    ],
    "ca364468": [
      2,
      0,
      13,
      15,
      17,
      12,
      16,
      14,
      4,
      3
    ],
    "d2041148": [
      2,
      0,
      13,
      15,
      17,
      12,
      16,
      14,
      4,
      3
    ],
    "59d8518b": [
      2,
      0,
      13,
      15,
      17,
      12,
      16,
      14,
      4,
      3
    ],
    "33d8dd06": [
      2,
      0,
      13,
      15,
      17,
      12,
      16,
      14,
      4,
      3
    ],
    "4361ef2e": [
      2,
      0,
      13,
      15,
      17,
      12,
      16,
      14,
      4,
      3
    ],
    "ba1e995c": [
      2,
      0,
      13,
      15,
      17,
      12,
      16,
      14,
      4,
      3
    ],
    "02f36b0d": [
      2,
      0,
      13,
      15,
      17,
      12,
      16,
      14,
      4,
      3
    ],
    "60eed69f": [
      2,
      0,
      13,
      15,
      17,
      12,
      16,
      14,
      4,
      3
    ],
    "e0ce4746": [
      2,
      0,
      13,
      15,
      17,
      12,
      16,
      14,
      4,
      3
    ],
    "8b3c010c": [
      2,
      0,
      13,
      15,
      17,
      12,
      16,
      14,
      4,
      3
    ],
    "507ef89f": [
      2,
      0,
      13,
      15,
      17,
      12,
      16,
      14,
      4,
      3
    ],
    "07b8247d": [
      2,
      0,
      13,
      15,
      17,
      12,
      16,
      14,
      4,
      3
    ],
    "13aaf3ee": [
      2,
      0,
      13,
      15,
      17,
      12,
      16,
      14,
      4,
      3
    ],
    "2bf19ada": [
      2,
      0,
      13,
      15,
      17,
      12,
      16,
      14,
      4,
      3
    ],
    "94a30312": [
      2,
      0,
      13,
      15,
      17,
      12,
      16,
      14,
      4,
      3
    ],
    "13921bde": [
      2,
      0,
      13,
      15,
      17,
      12,
      16,
      14,
      4,
      3
    ],
    "043cf666": [
      2,
      0,
      13,
      15,
      17,
      12,
      16,
      14,
      4,
      3
    ],
    "c0cab6d4": [
      2,
      0,
      13,
      15,
      17,
      12,
      16,
      14,
      4,
      3
    ],
    "72ca801d": [
      2,
      0,
      13,
      15,
      17,
      12,
      16,
      14,
      4,
      3
    ],
    "1e63418a": [
      2,
      0,
      13,
      15,
      17,
      12,
      16,
      14,
      4,
      3
    ],
    "c5566524": [
      2,
      0,
      13,
      15,
      17,
      12,
      16,
      14,
      4,
      3
    ],
    "0d771c53": [
      2,
      0,
      13,
      15,
      17,
      12,
      16,
      14,
      4,
      3
    ],
    "9f49dcb8": [
      2,
      0,
      13,
      15,
      17,
      12,
      16,
      14,
      4,
      3
    ],
    "cc05914a": [
      2,
      0,
      13,
      15,
      17,
      12,
      16,
      14,
      4,
      3
    ],
    "fb2c69d6": [
      2,
      0,
      13,
      15,
      17,
      12,
      16,
      14,
      4,
      3
    ],
    "3c873408": [
      2,
      0,
      13,
      15,
      17,
      12,
      16,
      14,
      4,
      3
    ],
    "6e428104": [
      2,
      0,
      13,
      15,
      17,
      12,
      16,
      14,
      4,
      3
    ],
    "6ddac5e4": [
      2,
      0,
      13,
      15,
      17,
      12,
      16,
      14,
      4,
      3
    ],
    "ca23b436": [
      2,
      0,
      13,
      15,
      17,
      12,
      16,
      14,
      4,
      3
    ],
    "0aea9007": [
      2,
      0,
      13,
      15,
      17,
      12,
      16,
      14,
      4,
      3
    ],
    "a9ca4f04": [
      2,
      0,
      13,
      15,
      17,
      12,
      16,
      14,
      4,
      3
    ],
    "2cb15d58": [
      2,
      0,
      13,
      15,
      17,
      12,
      16,
      14,
      4,
      3
    ],
    "2b27f4a7": [
      2,
      0,
      13,
      15,
      17,
      12,
      16,
      14,
      4,
      3
    ],
    "2cdccd46": [
      2,
      0,
      13,
      15,
      17,
      12,
      16,
      14,
      4,
      3
    ],
    "0a8a3814": [
      2,
      0,
      13,
      15,
      17,
      12,
      16,
      14,
      4,
      3
    ],
    "4ffaeaad": [
      2,
      0,
      13,
      15,
      17,
      12,
      16,
      14,
      4,
      3
    ],
    "7545c1d7": [
      2,
      0,
      13,
      15,
      17,
      12,
      16,
      14,
      4,
      3
    ],
    "72a01940": [
      2,
      0,
      13,
      15,
      17,
      12,
      16,
      14,
      4,
      3
    ],
    "c2ec3412": [
      2,
      0,
      13,
      15,
      17,
      12,
      16,
      14,
      4,
      3
    ],
    "73d106ed": [
      2,
      0,
      13,
      15,
      17,
      12,
      16,
      14,
      4,
      3
    ],
    "3cb143e4": [
      2,
      0,
      13,
      15,
      17,
      12,
      16,
      14,
      4,
      3
    ],
    "6b48667d": [
      2,
      0,
      13,
      15,
      17,
      12,
      16,
      14,
      4,
      3
    ],
    "637bf5f2": [
      2,
      0,
      13,
      15,
      17,
      12,
      16,
      14,
      4,
      3
    ],
    "b4441a04": [
      2,
      0,
      13,
      15,
      17,
      12,
      16,
      14,
      4,
      3
    ],
    "7b2197a7": [
      2,
      0,
      13,
      15,
      17,
      12,
      16,
      14,
      4,
      3
    ],
    "73d1817e": [
      2,
      0,
      13,
      15,
      17,
      12,
      16,
      14,
      4,
      3
    ],
    "71c6adb3": [
      2,
      0,
      13,
      15,
      17,
      12,
      16,
      14,
      4,
      3
    ],
    "749d2a46": [
      2,
      0,
      13,
      15,
      17,
      12,
      16,
      14,
      4,
      3
    ],
    "ac44a3cc": [
      2,
      0,
      13,
      15,
      17,
      12,
      16,
      14,
      4,
      3
    ],
    "551d8a1b": [
      2,
      0,
      13,
      15,
      17,
      12,
      16,
      14,
      4,
      3
    ],
    "1cd80c32": [
      2,
      0,
      13,
      15,
      17,
      12,
      16,
      14,
      4,
      3
    ],
    "0124be2e": [
      2,
      0,
      13,
      15,
      17,
      12,
      16,
      14,
      4,
      3
    ],
    "aec78abc": [
      2,
      0,
      13,
      15,
      17,
      12,
      16,
      14,
      4,
      3
    ],
    "5fbff510": [
      2,
      0,
      13,
      15,
      17,
      12,
      16,
      14,
      4,
      3
    ],
    "19be23fb": [
      2,
      0,
      13,
      15,
      17,
      12,
      16,
      14,
      4,
      3
    ],
    "3386d90e": [
      2,
      0,
      13,
      15,
      17,
      12,
      16,
      14,
      4,
      3
    ],
    "6cbb9f9a": [
      2,
      0,
      13,
      15,
      17,
      12,
      16,
      14,
      4,
      3
    ],
    "fe9a853c": [
      2,
      0,
      13,
      15,
      17,
      12,
      16,
      14,
      4,
      3
    ],
    "b7e8cb98": [
      2,
      0,
      13,
      15,
      17,
      12,
      16,
      14,
      4,
      3
    ],
    "6085951c": [
      2,
      0,
      13,
      15,
      17,
      12,
      16,
      14,
      4,
      3
    ],
    "11725a7d": [
      2,
      0,
      13,
      15,
      17,
      12,
      16,
      14,
      4,
      3
    ],
    "490ef3c8": [
      2,
      0,
      13,
      15,
      17,
      12,
      16,
      14,
      4,
      3
    ],
    "64e34622": [
      2,
      0,
      13,
      15,
      17,
      12,
      16,
      14,
      4,
      3
    ],
    "537ae026": [
      2,
      0,
      13,
      15,
      17,
      12,
      16,
      14,
      4,
      3
    ],
    "2ac2d26a": [
      2,
      0,
      13,
      15,
      17,
      12,
      16,
      14,
      4,
      3
    ],
    "3cfb1d2f": [
      2,
      0,
      13,
      15,
      17,
      12,
      16,
      14,
      4,
      3
    ],
    "bf4644b6": [
      2,
      0,
      13,
      15,
      17,
      12,
      16,
      14,
      4,
      3
    ],
    "0cb81350": [
      2,
      0,
      13,
      15,
      17,
      12,
      16,
      14,
      4,
      3
    ],
    "8540f91e": [
      2,
      0,
      13,
      15,
      17,
      12,
      16,
      14,
      4,
      3
    ],
    "5668ebba": [
      2,
      0,
      13,
      15,
      17,
      12,
      16,
      14,
      4,
      3
    ],
    "2de800b4": [
      2,
      0,
      13,
      15,
      17,
      12,
      16,
      14,
      4,
      3
    ],
    "1dbd3c7a": [
      2,
      0,
      13,
      15,
      17,
      12,
      16,
      14,
      4,
      3
    ],
    "2705e6a4": [
      2,
      0,
      13,
      15,
      17,
      12,
      16,
      14,
      4,
      3
    ],
    "19abd094": [
      2,
      0,
      13,
      15,
      17,
      12,
      16,
      14,
      4,
      3
    ],
    "21c7df22": [
      2,
      0,
      13,
      15,
      17,
      12,
      16,
      14,
      4,
      3
    ],
    "51d1e140": [
      2,
      0,
      13,
      15,
      17,
      12,
      16,
      14,
      4,
      3
    ],
    "f1ca8794": [
      2,
      0,
      13,
      15,
      17,
      12,
      16,
      14,
      4,
      3
    ],
    "582338f7": [
      2,
      0,
      13,
      15,
      17,
      12,
      16,
      14,
      4,
      3
    ],
    "37bb22ea": [
      2,
      0,
      13,
      15,
      17,
      12,
      16,
      14,
      4,
      3
    ],
    "629f9f90": [
      2,
      0,
      13,
      15,
      17,
      12,
      16,
      14,
      4,
      3
    ],
    "15ffecb3": [
      2,
      0,
      13,
      15,
      17,
      12,
      16,
      14,
      4,
      3
    ],
    "12f2e93c": [
      2,
      0,
      13,
      15,
      17,
      12,
      16,
      14,
      4,
      3
    ],
    "721a4ef3": [
      2,
      0,
      13,
      15,
      17,
      12,
      16,
      14,
      4,
      3
    ],
    "99ae3780": [
      2,
      0,
      13,
      15,
      17,
      12,
      16,
      14,
      4,
      3
    ],
    "927467d2": [
      2,
      0,
      13,
      15,
      17,
      12,
      16,
      14,
      4,
      3
    ],
    "4d1e306c": [
      2,
      0,
      13,
      15,
      17,
      12,
      16,
      14,
      4,
      3
    ],
    "f9dc2f76": [
      2,
      0,
      13,
      15,
      17,
      12,
      16,
      14,
      4,
      3
    ],
    "78bf771a": [
      2,
      0,
      13,
      15,
      17,
      12,
      16,
      14,
      4,
      3
    ],
    "5c7a30aa": [
      2,
      0,
      13,
      15,
      17,
      12,
      16,
      14,
      4,
      3
    ],
    "d0e7e08e": [
      2,
      0,
      13,
      15,
      17,
      12,
      16,
      14,
      4,
      3
    ],
    "8971bef0": [
      2,
      0,
      13,
      15,
      17,
      12,
      16,
      14,
      4,
      3
    ],
    "ed7ae168": [
      2,
      0,
      13,
      15,
      17,
      12,
      16,
      14,
      4,
      3
    ],
    "3bd65d90": [
      2,
      0,
      13,
      15,
      17,
      12,
      16,
      14,
      4,
      3
    ],
    "da4820fc": [
      2,
      0,
      13,
      15,
      17,
      12,
      16,
      14,
      4,
      3
    ],
    "310c012e": [
      2,
      0,
      13,
      15,
      17,
      12,
      16,
      14,
      4,
      3
    ],
    "466079d2": [
      2,
      0,
      13,
      15,
      17,
      12,
      16,
      14,
      4,
      3
    ],
    "095efcd8": [
      2,
      0,
      13,
      15,
      17,
      12,
      16,
      14,
      4,
      3
    ],
    "6ee0461a": [
      2,
      0,
      13,
      15,
      17,
      12,
      16,
      14,
      4,
      3
    ],
    "543f8040": [
      2,
      0,
      13,
      15,
      17,
      12,
      16,
      14,
      4,
      3
    ],
    "48292bbc": [
      2,
      0,
      13,
      15,
      17,
      12,
      16,
      14,
      4,
      3
    ],
    "d0c84124": [
      2,
      0,
      13,
      15,
      17,
      12,
      16,
      14,
      4,
      3
    ],
    "1e7c35d8": [
      2,
      0,
      13,
      15,
      17,
      12,
      16,
      14,
      4,
      3
    ],
    "a831faba": [
      2,
      0,
      13,
      15,
      17,
      12,
      16,
      14,
      4,
      3
    ],
    "2e184c1e": [
      2,
      0,
      13,
      15,
      17,
      12,
      16,
      14,
      4,
      3
    ],
    "26ab6ef8": [
      2,
      0,
      13,
      15,
      17,
      12,
      16,
      14,
      4,
      3
    ],
    "8d2adbda": [
      2,
      0,
      13,
      15,
      17,
      12,
      16,
      14,
      4,
      3
    ],
    "3929d25e": [
      2,
      0,
      13,
      15,
      17,
      12,
      16,
      14,
      4,
      3
    ],
    "4ec64bb3": [
      2,
      0,
      13,
      15,
      17,
      12,
      16,
      14,
      4,
      3
    ],
    "07e916be": [
      2,
      0,
      13,
      15,
      17,
      12,
      16,
      14,
      4,
      3
    ],
    "543ab1c1": [
      2,
      0,
      13,
      15,
      17,
      12,
      16,
      14,
      4,
      3
    ],
    "3308b5be": [
      2,
      0,
      13,
      15,
      17,
      12,
      16,
      14,
      4,
      3
    ],
    "00a81483": [
      2,
      0,
      13,
      15,
      17,
      12,
      16,
      14,
      4,
      3
    ],
    "66ccac90": [
      2,
      0,
      13,
      15,
      17,
      12,
      16,
      14,
      4,
      3
    ],
    "5aa338df": [
      2,
      0,
      13,
      15,
      17,
      12,
      16,
      14,
      4,
      3
    ],
    "134e89d2": [
      2,
      0,
      13,
      15,
      17,
      12,
      16,
      14,
      4,
      3
    ],
    "8d9f267a": [
      2,
      0,
      13,
      15,
      17,
      12,
      16,
      14,
      4,
      3
    ],
    "6063ad0a": [
      2,
      0,
      13,
      15,
      17,
      12,
      16,
      14,
      4,
      3
    ],
    "02b7d514": [
      2,
      0,
      13,
      15,
      17,
      12,
      16,
      14,
      4,
      3
    ],
    "ad1e7774": [
      2,
      0,
      13,
      15,
      17,
      12,
      16,
      14,
      4,
      3
    ],
    "d2f1985c": [
      2,
      0,
      13,
      15,
      17,
      12,
      16,
      14,
      4,
      3
    ],
    "2d50b08e": [
      2,
      0,
      13,
      15,
      17,
      12,
      16,
      14,
      4,
      3
    ],
    "09750e90": [
      2,
      0,
      13,
      15,
      17,
      12,
      16,
      14,
      4,
      3
    ],
    "9a3699d4": [
      2,
      0,
      13,
      15,
      17,
      12,
      16,
      14,
      4,
      3
    ],
    "2ed75be7": [
      2,
      0,
      13,
      15,
      17,
      12,
      16,
      14,
      4,
      3
    ],
    "5580a474": [
      2,
      0,
      13,
      15,
      17,
      12,
      16,
      14,
      4,
      3
    ],
    "094c0b49": [
      2,
      0,
      13,
      15,
      17,
      12,
      16,
      14,
      4,
      3
    ],
    "398a104c": [
      2,
      0,
      13,
      15,
      17,
      12,
      16,
      14,
      4,
      3
    ],
    "1c1c87a8": [
      2,
      0,
      13,
      15,
      17,
      12,
      16,
      14,
      4,
      3
    ],
    "55871bb6": [
      2,
      0,
      13,
      15,
      17,
      12,
      16,
      14,
      4,
      3
    ],
    "4233a514": [
      2,
      0,
      13,
      15,
      17,
      12,
      16,
      14,
      4,
      3
    ],
    "6420c1e0": [
      2,
      0,
      13,
      15,
      17,
      12,
      16,
      14,
      4,
      3
    ],
    "0b6d939e": [
      2,
      0,
      13,
      15,
      17,
      12,
      16,
      14,
      4,
      3
    ],
    "c0017abc": [
      2,
      0,
      13,
      15,
      17,
      12,
      16,
      14,
      4,
      3
    ],
    "0e0eea7c": [
      2,
      0,
      13,
      15,
      17,
      12,
      16,
      14,
      4,
      3
    ],
    "46ff121d": [
      2,
      0,
      13,
      15,
      17,
      12,
      16,
      14,
      4,
      3
    ],
    "3a870d94": [
      2,
      0,
      13,
      15,
      17,
      12,
      16,
      14,
      4,
      3
    ],
    "51db0568": [
      2,
      0,
      13,
      15,
      17,
      12,
      16,
      14,
      4,
      3
    ],
    "50c05446": [
      2,
      0,
      13,
      15,
      17,
      12,
      16,
      14,
      4,
      3
    ],
    "412548d3": [
      2,
      0,
      13,
      15,
      17,
      12,
      16,
      14,
      4,
      3
    ],
    "51ff2d78": [
      2,
      0,
      13,
      15,
      17,
      12,
      16,
      14,
      4,
      3
    ],
    "6eed0814": [
      2,
      0,
      13,
      15,
      17,
      12,
      16,
      14,
      4,
      3
    ],
    "f7b03708": [
      2,
      0,
      13,
      15,
      17,
      12,
      16,
      14,
      4,
      3
    ],
    "29e9f02f": [
      2,
      0,
      13,
      15,
      17,
      12,
      16,
      14,
      4,
      3
    ],
    "325815e3": [
      2,
      0,
      13,
      15,
      17,
      12,
      16,
      14,
      4,
      3
    ],
    "05616bae": [
      2,
      0,
      13,
      15,
      17,
      12,
      16,
      14,
      4,
      3
    ],
    "7c7ba3c1": [
      2,
      0,
      13,
      15,
      17,
      12,
      16,
      14,
      4,
      3
    ],
    "6b0c7441": [
      2,
      0,
      13,
      15,
      17,
      12,
      16,
      14,
      4,
      3
    ],
    "12bee0cc": [
      2,
      0,
      13,
      15,
      17,
      12,
      16,
      14,
      4,
      3
    ],
    "3a8f9460": [
      2,
      0,
      13,
      15,
      17,
      12,
      16,
      14,
      4,
      3
    ],
    "00ede510": [
      2,
      0,
      13,
      15,
      17,
      12,
      16,
      14,
      4,
      3
    ],
    "5effccde": [
      2,
      0,
      13,
      15,
      17,
      12,
      16,
      14,
      4,
      3
    ],
    "046dca92": [
      2,
      0,
      13,
      15,
      17,
      12,
      16,
      14,
      4,
      3
    ],
    "65409aed": [
      2,
      0,
      13,
      15,
      17,
      12,
      16,
      14,
      4,
      3
    ],
    "991a5a00": [
      2,
      0,
      13,
      15,
      17,
      12,
      16,
      14,
      4,
      3
    ],
    "39d3def8": [
      2,
      0,
      13,
      15,
      17,
      12,
      16,
      14,
      4,
      3
    ],
    "86c5e944": [
      2,
      0,
      13,
      15,
      17,
      12,
      16,
      14,
      4,
      3
    ],
    "fdfddf18": [
      2,
      0,
      13,
      15,
      17,
      12,
      16,
      14,
      4,
      3
    ],
    "aa02b31c": [
      2,
      0,
      13,
      15,
      17,
      12,
      16,
      14,
      4,
      3
    ],
    "e6e95032": [
      2,
      0,
      13,
      15,
      17,
      12,
      16,
      14,
      4,
      3
    ],
    "dd9ae166": [
      2,
      0,
      13,
      15,
      17,
      12,
      16,
      14,
      4,
      3
    ],
    "14a233bd": [
      2,
      0,
      13,
      15,
      17,
      12,
      16,
      14,
      4,
      3
    ],
    "350c1de2": [
      2,
      0,
      13,
      15,
      17,
      12,
      16,
      14,
      4,
      3
    ],
    "62e4efab": [
      2,
      0,
      13,
      15,
      17,
      12,
      16,
      14,
      4,
      3
    ],
    "93fccc08": [
      2,
      0,
      13,
      15,
      17,
      12,
      16,
      14,
      4,
      3
    ],
    "7aeb41bb": [
      2,
      0,
      13,
      15,
      17,
      12,
      16,
      14,
      4,
      3
    ],
    "00247a2a": [
      2,
      0,
      13,
      15,
      17,
      12,
      16,
      14,
      4,
      3
    ],
    "4b53b468": [
      2,
      0,
      13,
      15,
      17,
      12,
      16,
      14,
      4,
      3
    ],
    "acd23898": [
      2,
      0,
      13,
      15,
      17,
      12,
      16,
      14,
      4,
      3
    ],
    "438e6540": [
      2,
      0,
      13,
      15,
      17,
      12,
      16,
      14,
      4,
      3
    ],
    "7966a074": [
      2,
      0,
      13,
      15,
      17,
      12,
      16,
      14,
      4,
      3
    ],
    "5661ccf4": [
      2,
      0,
      13,
      15,
      17,
      12,
      16,
      14,
      4,
      3
    ],
    "a38308f4": [
      2,
      0,
      13,
      15,
      17,
      12,
      16,
      14,
      4,
      3
    ],
    "b3097cfa": [
      2,
      0,
      13,
      15,
      17,
      12,
      16,
      14,
      4,
      3
    ],
    "3275fdad": [
      2,
      0,
      13,
      15,
      17,
      12,
      16,
      14,
      4,
      3
    ],
    "735d9990": [
      2,
      0,
      13,
      15,
      17,
      12,
      16,
      14,
      4,
      3
    ],
    "4ac37487": [
      2,
      0,
      13,
      15,
      17,
      12,
      16,
      14,
      4,
      3
    ],
    "1c08d615": [
      2,
      0,
      13,
      15,
      17,
      12,
      16,
      14,
      4,
      3
    ],
    "e78e9122": [
      2,
      0,
      13,
      15,
      17,
      12,
      16,
      14,
      4,
      3
    ],
    "0889a916": [
      2,
      0,
      13,
      15,
      17,
      12,
      16,
      14,
      4,
      3
    ],
    "004545d2": [
      2,
      0,
      13,
      15,
      17,
      12,
      16,
      14,
      4,
      3
    ],
    "26d3fa54": [
      2,
      0,
      13,
      15,
      17,
      12,
      16,
      14,
      4,
      3
    ],
    "2ac8c29e": [
      2,
      0,
      13,
      15,
      17,
      12,
      16,
      14,
      4,
      3
    ],
    "3cc4d4be": [
      2,
      0,
      13,
      15,
      17,
      12,
      16,
      14,
      4,
      3
    ],
    "57eb387f": [
      2,
      0,
      13,
      15,
      17,
      12,
      16,
      14,
      4,
      3
    ],
    "56a8ae97": [
      2,
      0,
      13,
      15,
      17,
      12,
      16,
      14,
      4,
      3
    ],
    "42d1f950": [
      2,
      0,
      13,
      15,
      17,
      12,
      16,
      14,
      4,
      3
    ],
    "1734d68a": [
      2,
      0,
      13,
      15,
      17,
      12,
      16,
      14,
      4,
      3
    ],
    "63ba0e76": [
      2,
      0,
      13,
      15,
      17,
      12,
      16,
      14,
      4,
      3
    ],
    "671c86f8": [
      2,
      0,
      13,
      15,
      17,
      12,
      16,
      14,
      4,
      3
    ],
    "bd60c23a": [
      2,
      0,
      13,
      15,
      17,
      12,
      16,
      14,
      4,
      3
    ],
    "02e75f92": [
      2,
      0,
      13,
      15,
      17,
      12,
      16,
      14,
      4,
      3
    ],
    "275c1a8c": [
      36
    ],
    "6e0a9004": [
      2,
      0,
      13,
      15,
      17,
      12,
      16,
      14,
      4,
      3
    ],
    "995bcfa4": [
      36
    ],
    "628f1226": [
      36
    ],
    "1a3afa17": [
      2,
      0,
      13,
      15,
      17,
      12,
      16,
      14,
      4,
      3
    ],
    "3a0d8076": [
      2,
      0,
      13,
      15,
      17,
      12,
      16,
      14,
      4,
      3
    ],
    "5d7b6ea1": [
      2,
      0,
      13,
      15,
      17,
      12,
      16,
      14,
      4,
      3
    ],
    "26a55028": [
      2,
      0,
      13,
      15,
      17,
      12,
      16,
      14,
      4,
      3
    ],
    "7f00a82a": [
      2,
      0,
      13,
      15,
      17,
      12,
      16,
      14,
      4,
      3
    ],
    "f3645140": [
      2,
      0,
      13,
      15,
      17,
      12,
      16,
      14,
      4,
      3
    ],
    "4daed36c": [
      2,
      0,
      13,
      15,
      17,
      12,
      16,
      14,
      4,
      3
    ],
    "3d9a1aa1": [
      2,
      0,
      13,
      15,
      17,
      12,
      16,
      14,
      4,
      3
    ],
    "743615fc": [
      2,
      0,
      13,
      15,
      17,
      12,
      16,
      14,
      4,
      3
    ],
    "3e38888e": [
      2,
      0,
      13,
      15,
      17,
      12,
      16,
      14,
      4,
      3
    ],
    "3c2ade3f": [
      2,
      0,
      13,
      15,
      17,
      12,
      16,
      14,
      4,
      3
    ],
    "7b5f21c7": [
      2,
      0,
      13,
      15,
      17,
      12,
      16,
      14,
      4,
      3
    ],
    "2a95c6b0": [
      2,
      0,
      13,
      15,
      17,
      12,
      16,
      14,
      4,
      3
    ],
    "1024b6d2": [
      2,
      0,
      13,
      15,
      17,
      12,
      16,
      14,
      4,
      3
    ],
    "9068f2ea": [
      2,
      0,
      13,
      15,
      17,
      12,
      16,
      14,
      4,
      3
    ],
    "2627016c": [
      2,
      0,
      13,
      15,
      17,
      12,
      16,
      14,
      4,
      3
    ],
    "cfddf402": [
      2,
      0,
      13,
      15,
      17,
      12,
      16,
      14,
      4,
      3
    ],
    "27f17f72": [
      2,
      0,
      13,
      15,
      17,
      12,
      16,
      14,
      4,
      3
    ],
    "09a8b322": [
      2,
      0,
      13,
      15,
      17,
      12,
      16,
      14,
      4,
      3
    ],
    "95fab5a8": [
      2,
      0,
      13,
      15,
      17,
      12,
      16,
      14,
      4,
      3
    ],
    "e6bbe71a": [
      2,
      0,
      13,
      15,
      17,
      12,
      16,
      14,
      4,
      3
    ],
    "63275f66": [
      2,
      0,
      13,
      15,
      17,
      12,
      16,
      14,
      4,
      3
    ],
    "6b4d126c": [
      2,
      0,
      13,
      15,
      17,
      12,
      16,
      14,
      4,
      3
    ],
    "2568f631": [
      2,
      0,
      13,
      15,
      17,
      12,
      16,
      14,
      4,
      3
    ],
    "0adfd9d1": [
      2,
      0,
      13,
      15,
      17,
      12,
      16,
      14,
      4,
      3
    ],
    "33189d37": [
      2,
      0,
      13,
      15,
      17,
      12,
      16,
      14,
      4,
      3
    ],
    "27aa65fe": [
      2,
      0,
      13,
      15,
      17,
      12,
      16,
      14,
      4,
      3
    ],
    "8452ab58": [
      2,
      0,
      13,
      15,
      17,
      12,
      16,
      14,
      4,
      3
    ],
    "01f8810a": [
      2,
      0,
      13,
      15,
      17,
      12,
      16,
      14,
      4,
      3
    ],
    "79a86fc4": [
      2,
      0,
      13,
      15,
      17,
      12,
      16,
      14,
      4,
      3
    ],
    "1d6536aa": [
      2,
      0,
      13,
      15,
      17,
      12,
      16,
      14,
      4,
      3
    ],
    "7eba18f1": [
      2,
      0,
      13,
      15,
      17,
      12,
      16,
      14,
      4,
      3
    ],
    "8e57339c": [
      2,
      0,
      13,
      15,
      17,
      12,
      16,
      14,
      4,
      3
    ],
    "692e724a": [
      2,
      0,
      13,
      15,
      17,
      12,
      16,
      14,
      4,
      3
    ],
    "61255e88": [
      2,
      0,
      13,
      15,
      17,
      12,
      16,
      14,
      4,
      3
    ],
    "e4c86c8e": [
      2,
      0,
      13,
      15,
      17,
      12,
      16,
      14,
      4,
      3
    ],
    "4ba92109": [
      2,
      0,
      13,
      15,
      17,
      12,
      16,
      14,
      4,
      3
    ],
    "b75663e6": [
      2,
      0,
      13,
      15,
      17,
      12,
      16,
      14,
      4,
      3
    ],
    "7453e594": [
      2,
      0,
      13,
      15,
      17,
      12,
      16,
      14,
      4,
      3
    ],
    "6326474e": [
      2,
      0,
      13,
      15,
      17,
      12,
      16,
      14,
      4,
      3
    ],
    "4eb254a1": [
      2,
      0,
      13,
      15,
      17,
      12,
      16,
      14,
      4,
      3
    ],
    "60c00eeb": [
      2,
      0,
      13,
      15,
      17,
      12,
      16,
      14,
      4,
      3
    ],
    "a2c9b316": [
      2,
      0,
      13,
      15,
      17,
      12,
      16,
      14,
      4,
      3
    ],
    "1807d528": [
      2,
      0,
      13,
      15,
      17,
      12,
      16,
      14,
      4,
      3
    ],
    "3e56090e": [
      2,
      0,
      13,
      15,
      17,
      12,
      16,
      14,
      4,
      3
    ],
    "12f12772": [
      2,
      0,
      13,
      15,
      17,
      12,
      16,
      14,
      4,
      3
    ],
    "1c4550b0": [
      2,
      0,
      13,
      15,
      17,
      12,
      16,
      14,
      4,
      3
    ],
    "43a308ba": [
      2,
      0,
      13,
      15,
      17,
      12,
      16,
      14,
      4,
      3
    ],
    "1e2bb9d4": [
      2,
      0,
      13,
      15,
      17,
      12,
      16,
      14,
      4,
      3
    ],
    "1fd32854": [
      2,
      0,
      13,
      15,
      17,
      12,
      16,
      14,
      4,
      3
    ],
    "11486cfe": [
      2,
      0,
      13,
      15,
      17,
      12,
      16,
      14,
      4,
      3
    ],
    "29f440fd": [
      2,
      0,
      13,
      15,
      17,
      12,
      16,
      14,
      4,
      3
    ],
    "7e3de8f0": [
      2,
      0,
      13,
      15,
      17,
      12,
      16,
      14,
      4,
      3
    ],
    "02a3dafa": [
      2,
      0,
      13,
      15,
      17,
      12,
      16,
      14,
      4,
      3
    ],
    "2fc4657e": [
      2,
      0,
      13,
      15,
      17,
      12,
      16,
      14,
      4,
      3
    ],
    "b8e4eb68": [
      2,
      0,
      13,
      15,
      17,
      12,
      16,
      14,
      4,
      3
    ],
    "8e3afaea": [
      2,
      0,
      13,
      15,
      17,
      12,
      16,
      14,
      4,
      3
    ],
    "2277051a": [
      2,
      0,
      13,
      15,
      17,
      12,
      16,
      14,
      4,
      3
    ],
    "d9a08fe2": [
      2,
      0,
      13,
      15,
      17,
      12,
      16,
      14,
      4,
      3
    ],
    "c1d731d2": [
      2,
      0,
      13,
      15,
      17,
      12,
      16,
      14,
      4,
      3
    ],
    "18ea00c9": [
      2,
      0,
      13,
      15,
      17,
      12,
      16,
      14,
      4,
      3
    ],
    "2a1258df": [
      2,
      0,
      13,
      15,
      17,
      12,
      16,
      14,
      4,
      3
    ],
    "7e77f1c7": [
      2,
      0,
      13,
      15,
      17,
      12,
      16,
      14,
      4,
      3
    ],
    "aba671ec": [
      2,
      0,
      13,
      15,
      17,
      12,
      16,
      14,
      4,
      3
    ],
    "2d909008": [
      2,
      0,
      13,
      15,
      17,
      12,
      16,
      14,
      4,
      3
    ],
    "88f07b3e": [
      2,
      0,
      13,
      15,
      17,
      12,
      16,
      14,
      4,
      3
    ],
    "57a38c46": [
      2,
      0,
      13,
      15,
      17,
      12,
      16,
      14,
      4,
      3
    ],
    "00676728": [
      2,
      0,
      13,
      15,
      17,
      12,
      16,
      14,
      4,
      3
    ],
    "22eaca6e": [
      2,
      0,
      13,
      15,
      17,
      12,
      16,
      14,
      4,
      3
    ],
    "213db4c0": [
      2,
      0,
      13,
      15,
      17,
      12,
      16,
      14,
      4,
      3
    ],
    "3c32e35c": [
      2,
      0,
      13,
      15,
      17,
      12,
      16,
      14,
      4,
      3
    ],
    "272e0b24": [
      2,
      0,
      13,
      15,
      17,
      12,
      16,
      14,
      4,
      3
    ],
    "3209eee4": [
      2,
      0,
      13,
      15,
      17,
      12,
      16,
      14,
      4,
      3
    ],
    "4ec4a0df": [
      2,
      0,
      13,
      15,
      17,
      12,
      16,
      14,
      4,
      3
    ],
    "2b89a35c": [
      2,
      0,
      13,
      15,
      17,
      12,
      16,
      14,
      4,
      3
    ],
    "2c540628": [
      2,
      0,
      13,
      15,
      17,
      12,
      16,
      14,
      4,
      3
    ],
    "1715b966": [
      2,
      0,
      13,
      15,
      17,
      12,
      16,
      14,
      4,
      3
    ],
    "c44d641a": [
      2,
      0,
      13,
      15,
      17,
      12,
      16,
      14,
      4,
      3
    ],
    "7fb7b99a": [
      2,
      0,
      13,
      15,
      17,
      12,
      16,
      14,
      4,
      3
    ],
    "240f7be7": [
      2,
      0,
      13,
      15,
      17,
      12,
      16,
      14,
      4,
      3
    ],
    "408244ae": [
      2,
      0,
      13,
      15,
      17,
      12,
      16,
      14,
      4,
      3
    ],
    "6cd12e46": [
      2,
      0,
      13,
      15,
      17,
      12,
      16,
      14,
      4,
      3
    ],
    "6ce4dd96": [
      2,
      0,
      13,
      15,
      17,
      12,
      16,
      14,
      4,
      3
    ],
    "a234ebe0": [
      2,
      0,
      13,
      15,
      17,
      12,
      16,
      14,
      4,
      3
    ],
    "817fc70c": [
      2,
      0,
      13,
      15,
      17,
      12,
      16,
      14,
      4,
      3
    ],
    "7a8b66e8": [
      2,
      0,
      13,
      15,
      17,
      12,
      16,
      14,
      4,
      3
    ],
    "34f9b970": [
      2,
      0,
      13,
      15,
      17,
      12,
      16,
      14,
      4,
      3
    ],
    "0b19944d": [
      2,
      0,
      13,
      15,
      17,
      12,
      16,
      14,
      4,
      3
    ],
    "08487470": [
      2,
      0,
      13,
      15,
      17,
      12,
      16,
      14,
      4,
      3
    ],
    "718c5040": [
      2,
      0,
      13,
      15,
      17,
      12,
      16,
      14,
      4,
      3
    ],
    "14a1b5f1": [
      2,
      0,
      13,
      15,
      17,
      12,
      16,
      14,
      4,
      3
    ],
    "793594ca": [
      2,
      0,
      13,
      15,
      17,
      12,
      16,
      14,
      4,
      3
    ],
    "140811d2": [
      2,
      0,
      13,
      15,
      17,
      12,
      16,
      14,
      4,
      3
    ],
    "471cbb67": [
      2,
      0,
      13,
      15,
      17,
      12,
      16,
      14,
      4,
      3
    ],
    "28f02caa": [
      2,
      0,
      13,
      15,
      17,
      12,
      16,
      14,
      4,
      3
    ],
    "6f1fb0fa": [
      2,
      0,
      13,
      15,
      17,
      12,
      16,
      14,
      4,
      3
    ],
    "e9646504": [
      2,
      0,
      13,
      15,
      17,
      12,
      16,
      14,
      4,
      3
    ],
    "46c40046": [
      2,
      0,
      13,
      15,
      17,
      12,
      16,
      14,
      4,
      3
    ],
    "a4185f3a": [
      2,
      0,
      13,
      15,
      17,
      12,
      16,
      14,
      4,
      3
    ],
    "20b62bdc": [
      2,
      0,
      13,
      15,
      17,
      12,
      16,
      14,
      4,
      3
    ],
    "4b1f750b": [
      2,
      0,
      13,
      15,
      17,
      12,
      16,
      14,
      4,
      3
    ],
    "1b020123": [
      2,
      0,
      13,
      15,
      17,
      12,
      16,
      14,
      4,
      3
    ],
    "151114ea": [
      2,
      0,
      13,
      15,
      17,
      12,
      16,
      14,
      4,
      3
    ],
    "f54ffb48": [
      2,
      0,
      13,
      15,
      17,
      12,
      16,
      14,
      4,
      3
    ],
    "1c9be556": [
      2,
      0,
      13,
      15,
      17,
      12,
      16,
      14,
      4,
      3
    ],
    "f234930c": [
      2,
      0,
      13,
      15,
      17,
      12,
      16,
      14,
      4,
      3
    ],
    "f170c53c": [
      2,
      0,
      13,
      15,
      17,
      12,
      16,
      14,
      4,
      3
    ],
    "ab03f038": [
      2,
      0,
      13,
      15,
      17,
      12,
      16,
      14,
      4,
      3
    ],
    "0edb92f9": [
      2,
      0,
      13,
      15,
      17,
      12,
      16,
      14,
      4,
      3
    ],
    "ee273968": [
      2,
      0,
      13,
      15,
      17,
      12,
      16,
      14,
      4,
      3
    ],
    "70a520e5": [
      2,
      0,
      13,
      15,
      17,
      12,
      16,
      14,
      4,
      3
    ],
    "e59eb36e": [
      2,
      0,
      13,
      15,
      17,
      12,
      16,
      14,
      4,
      3
    ],
    "710b74ee": [
      2,
      0,
      13,
      15,
      17,
      12,
      16,
      14,
      4,
      3
    ],
    "5095801a": [
      2,
      0,
      13,
      15,
      17,
      12,
      16,
      14,
      4,
      3
    ],
    "6c52de8f": [
      2,
      0,
      13,
      15,
      17,
      12,
      16,
      14,
      4,
      3
    ],
    "2ffbd197": [
      2,
      0,
      13,
      15,
      17,
      12,
      16,
      14,
      4,
      3
    ],
    "26a88ae9": [
      2,
      0,
      13,
      15,
      17,
      12,
      16,
      14,
      4,
      3
    ],
    "fbf0a922": [
      2,
      0,
      13,
      15,
      17,
      12,
      16,
      14,
      4,
      3
    ],
    "ca10a12a": [
      2,
      0,
      13,
      15,
      17,
      12,
      16,
      14,
      4,
      3
    ],
    "c8c4a038": [
      2,
      0,
      13,
      15,
      17,
      12,
      16,
      14,
      4,
      3
    ],
    "0fae0034": [
      2,
      0,
      13,
      15,
      17,
      12,
      16,
      14,
      4,
      3
    ],
    "0ac8615c": [
      2,
      0,
      13,
      15,
      17,
      12,
      16,
      14,
      4,
      3
    ],
    "6acf89e8": [
      2,
      0,
      13,
      15,
      17,
      12,
      16,
      14,
      4,
      3
    ],
    "00717e2d": [
      2,
      0,
      13,
      15,
      17,
      12,
      16,
      14,
      4,
      3
    ],
    "7400f590": [
      2,
      0,
      13,
      15,
      17,
      12,
      16,
      14,
      4,
      3
    ],
    "5010459f": [
      2,
      0,
      13,
      15,
      17,
      12,
      16,
      14,
      4,
      3
    ],
    "5011a2bc": [
      2,
      0,
      13,
      15,
      17,
      12,
      16,
      14,
      4,
      3
    ],
    "7f904c9e": [
      2,
      0,
      13,
      15,
      17,
      12,
      16,
      14,
      4,
      3
    ],
    "8c64cdca": [
      2,
      0,
      13,
      15,
      17,
      12,
      16,
      14,
      4,
      3
    ],
    "2d8c8ea8": [
      2,
      0,
      13,
      15,
      17,
      12,
      16,
      14,
      4,
      3
    ],
    "7c296c69": [
      2,
      0,
      13,
      15,
      17,
      12,
      16,
      14,
      4,
      3
    ],
    "7a2c8d14": [
      2,
      0,
      13,
      15,
      17,
      12,
      16,
      14,
      4,
      3
    ],
    "16ebb9eb": [
      2,
      0,
      13,
      15,
      17,
      12,
      16,
      14,
      4,
      3
    ],
    "395e37ef": [
      2,
      0,
      13,
      15,
      17,
      12,
      16,
      14,
      4,
      3
    ],
    "7c8dafcc": [
      2,
      0,
      13,
      15,
      17,
      12,
      16,
      14,
      4,
      3
    ],
    "0885cd9a": [
      2,
      0,
      13,
      15,
      17,
      12,
      16,
      14,
      4,
      3
    ],
    "489bb150": [
      2,
      0,
      13,
      15,
      17,
      12,
      16,
      14,
      4,
      3
    ],
    "7e52a492": [
      2,
      0,
      13,
      15,
      17,
      12,
      16,
      14,
      4,
      3
    ],
    "6bfeb4dd": [
      2,
      0,
      13,
      15,
      17,
      12,
      16,
      14,
      4,
      3
    ],
    "24bcb1aa": [
      2,
      0,
      13,
      15,
      17,
      12,
      16,
      14,
      4,
      3
    ],
    "fc299812": [
      2,
      0,
      13,
      15,
      17,
      12,
      16,
      14,
      4,
      3
    ],
    "455780e1": [
      2,
      0,
      13,
      15,
      17,
      12,
      16,
      14,
      4,
      3
    ],
    "97a7fbe8": [
      2,
      0,
      13,
      15,
      17,
      12,
      16,
      14,
      4,
      3
    ],
    "886dec70": [
      2,
      0,
      13,
      15,
      17,
      12,
      16,
      14,
      4,
      3
    ],
    "adca6a36": [
      2,
      0,
      13,
      15,
      17,
      12,
      16,
      14,
      4,
      3
    ],
    "0911cd3d": [
      2,
      0,
      13,
      15,
      17,
      12,
      16,
      14,
      4,
      3
    ],
    "ce5258e0": [
      2,
      0,
      13,
      15,
      17,
      12,
      16,
      14,
      4,
      3
    ],
    "3895a019": [
      2,
      0,
      13,
      15,
      17,
      12,
      16,
      14,
      4,
      3
    ],
    "08a52546": [
      2,
      0,
      13,
      15,
      17,
      12,
      16,
      14,
      4,
      3
    ],
    "5ee3e1c3": [
      2,
      0,
      13,
      15,
      17,
      12,
      16,
      14,
      4,
      3
    ],
    "1670f96e": [
      2,
      0,
      13,
      15,
      17,
      12,
      16,
      14,
      4,
      3
    ],
    "a75f0452": [
      2,
      0,
      13,
      15,
      17,
      12,
      16,
      14,
      4,
      3
    ],
    "61971ec8": [
      2,
      0,
      13,
      15,
      17,
      12,
      16,
      14,
      4,
      3
    ],
    "86acc81a": [
      2,
      0,
      13,
      15,
      17,
      12,
      16,
      14,
      4,
      3
    ],
    "3b691e65": [
      2,
      0,
      13,
      15,
      17,
      12,
      16,
      14,
      4,
      3
    ],
    "66f50980": [
      2,
      0,
      13,
      15,
      17,
      12,
      16,
      14,
      4,
      3
    ],
    "8c4f8c8a": [
      2,
      0,
      13,
      15,
      17,
      12,
      16,
      14,
      4,
      3
    ],
    "709d68b6": [
      2,
      0,
      13,
      15,
      17,
      12,
      16,
      14,
      4,
      3
    ],
    "ba3e54a6": [
      2,
      0,
      13,
      15,
      17,
      12,
      16,
      14,
      4,
      3
    ],
    "42e938d8": [
      2,
      0,
      13,
      15,
      17,
      12,
      16,
      14,
      4,
      3
    ],
    "309dbadd": [
      2,
      0,
      13,
      15,
      17,
      12,
      16,
      14,
      4,
      3
    ],
    "d0cf8824": [
      2,
      0,
      13,
      15,
      17,
      12,
      16,
      14,
      4,
      3
    ],
    "79d7841e": [
      39,
      8
    ],
    "326c9dc8": [
      39,
      8
    ],
    "63bdd9a5": [
      39,
      8
    ],
    "40539bf4": [
      39,
      8
    ],
    "8da141ea": [
      39,
      8
    ],
    "76531ea6": [
      39,
      8
    ],
    "2f8877b3": [
      39,
      8
    ],
    "1628b813": [
      39,
      8
    ],
    "6fbc4fdc": [
      39,
      8
    ],
    "35b75c20": [
      39,
      8
    ],
    "7aa80c74": [
      39,
      8
    ],
    "6bb82dd6": [
      39,
      8
    ],
    "b79d39d0": [
      39,
      8
    ],
    "594d331d": [
      39,
      8
    ]
  }
}